{"product": {
    "brandName": "",
    "brandPartnumber": "",
    "categoriesParentList": {"categoryParent": {"categoryIdentifier": "portes-coulissantes_CCN0170"}},
    "imageFull": {"locale": "fr"},
    "published": {
        "locale": "fr",
        "content": false
    },
    "label": {
        "locale": "fr",
        "content": "Porte coulissante chêne plaqué Quadral pleine"
    },
    "type": "STANDARD",
    "additionalDesc1": {
        "locale": "fr",
        "content": "Porte bois à rive droite en Chêne plaqué à l'esthétique contemporaine. Fabriqué dans nos usines françaises. Existe également en version 4 panneaux vitrés sur ce site."
    },
    "additionalDesc2": {"locale": "fr"},
    "attributeValueList": {"attributeValue": [
        {
            "attrIdentifier": "CCU0004-DIMENSIONS-COMMUNES-DIM-LARGEUR",
            "attrUsage": 1,
            "attrSequence": 1
        },
        {
            "attrIdentifier": "categorieGoogle",
            "valueString": {
                "locale": "fr",
                "content": 119
            },
            "attrUsage": 2,
            "attrSequence": 0
        },
        {
            "attrIdentifier": "colissimo",
            "attrUsage": 2,
            "valueDecimal": {
                "locale": "fr",
                "content": 0
            },
            "attrSequence": 0
        },
        {
            "valueIdentifier": 0,
            "attrIdentifier": "contrainteColisage",
            "valueString": {
                "locale": "fr",
                "content": 0
            },
            "attrUsage": 2,
            "attrSequence": 0
        },
        {
            "attrIdentifier": "priceLabel",
            "valueString": {
                "locale": "fr",
                "content": "Prix pour la dimension H 204 x L 73 cm"
            },
            "attrUsage": 2,
            "attrSequence": 0
        },
        {
            "valueIdentifier": "UN",
            "attrIdentifier": "uniteSecondaire",
            "valueString": {
                "locale": "fr",
                "content": "UN"
            },
            "attrUsage": 2,
            "attrSequence": 0
        },
        {
            "valueIdentifier": "UN",
            "attrIdentifier": "uniteVente",
            "valueString": {
                "locale": "fr",
                "content": "UN"
            },
            "attrUsage": 2,
            "attrSequence": 0
        },
        {
            "valueIdentifier": "UN",
            "attrIdentifier": "uniteVenteLegale",
            "valueString": {
                "locale": "fr",
                "content": "UN"
            },
            "attrUsage": 2,
            "attrSequence": 0
        }
    ]},
    "action": "add",
    "shortDesc": {"locale": "fr"},
    "itemList": {"item": [
        {
            "attributeValueList": {"attributeValue": [
                {
                    "attrIdentifier": "ATC-AUSSI-SUR-MESURE",
                    "attrUsage": 2,
                    "valueDecimal": {
                        "locale": "fr",
                        "content": 0
                    },
                    "attrSequence": 0
                },
                {
                    "valueIdentifier": "K61",
                    "attrIdentifier": "ATC-CHANT",
                    "valueString": {
                        "locale": "fr",
                        "content": "Rive droite"
                    },
                    "attrUsage": 2,
                    "attrSequence": 0
                },
                {
                    "attrIdentifier": "ATC-COULEUR-CARTE",
                    "attrUsage": 2,
                    "valueDecimal": {
                        "locale": "fr",
                        "content": 0
                    },
                    "attrSequence": 0
                },
                {
                    "attrIdentifier": "ATC-FAB-EN-FRANCE",
                    "attrUsage": 2,
                    "valueDecimal": {
                        "locale": "fr",
                        "content": 0
                    },
                    "attrSequence": 0
                },
                {
                    "attrIdentifier": "ATC-FAB-PAR-LAPEYRE",
                    "attrUsage": 2,
                    "valueDecimal": {
                        "locale": "fr",
                        "content": 0
                    },
                    "attrSequence": 0
                },
                {
                    "valueIdentifier": "V47",
                    "attrIdentifier": "ATC-GAMME-SPECIFIQUE",
                    "valueString": {
                        "locale": "fr",
                        "content": "Portes intérieures"
                    },
                    "attrUsage": 2,
                    "attrSequence": 0
                },
                {
                    "attrIdentifier": "ATC-HAUTEUR-TOTALE",
                    "attrUsage": 2,
                    "valueDecimal": {
                        "locale": "fr",
                        "content": 204
                    },
                    "attrSequence": 0
                },
                {
                    "attrIdentifier": "ATC-LARGEUR-PASSAGE",
                    "attrUsage": 2,
                    "valueDecimal": {
                        "locale": "fr",
                        "content": 71.4
                    },
                    "attrSequence": 0
                },
                {
                    "attrIdentifier": "ATC-LARGEUR-TOTALE",
                    "attrUsage": 2,
                    "valueDecimal": {
                        "locale": "fr",
                        "content": 73
                    },
                    "attrSequence": 0
                },
                {
                    "attrIdentifier": "ATC-NORME-FSC",
                    "attrUsage": 2,
                    "valueDecimal": {
                        "locale": "fr",
                        "content": 0
                    },
                    "attrSequence": 0
                },
                {
                    "attrIdentifier": "ATC-NORME-PEFC",
                    "attrUsage": 2,
                    "valueDecimal": {
                        "locale": "fr",
                        "content": 0
                    },
                    "attrSequence": 0
                },
                {
                    "valueIdentifier": "K31",
                    "attrIdentifier": "ATC-PRODUIT",
                    "valueString": {
                        "locale": "fr",
                        "content": "Porte coulissante"
                    },
                    "attrUsage": 2,
                    "attrSequence": 0
                },
                {
                    "attrIdentifier": "ATD-CategorieCDG",
                    "valueString": {
                        "locale": "fr",
                        "content": "G3876-PORTES CHENE PLAQUE"
                    },
                    "attrUsage": 2,
                    "attrSequence": 0
                },
                {
                    "attrIdentifier": "ATD-FamilleCDG",
                    "valueString": {
                        "locale": "fr",
                        "content": "G17-PORTES INTERIEURES"
                    },
                    "attrUsage": 2,
                    "attrSequence": 0
                },
                {
                    "attrIdentifier": "ATD-LibelleCommercial",
                    "valueString": {
                        "locale": "fr",
                        "content": "Porte coulissante QUADRAL 4 panneaux plaqués chêne H.204 x l.73 cm"
                    },
                    "attrUsage": 2,
                    "attrSequence": 0
                },
                {
                    "attrIdentifier": "ATD-SousCategorieCDG",
                    "valueString": {
                        "locale": "fr",
                        "content": "G13166-QUADRAL PLEIN"
                    },
                    "attrUsage": 2,
                    "attrSequence": 0
                },
                {
                    "attrIdentifier": "ATD-SousCategorieCDG2",
                    "valueString": {
                        "locale": "fr",
                        "content": "2550910-PS COUL QUADRAL 4 PANNEAUX 204X73"
                    },
                    "attrUsage": 2,
                    "attrSequence": 0
                },
                {
                    "attrIdentifier": "ATD-SousCategorieCDG3",
                    "valueString": {
                        "locale": "fr",
                        "content": "N/A"
                    },
                    "attrUsage": 2,
                    "attrSequence": 0
                },
                {
                    "attrIdentifier": "ATD-SousFamilleCDG",
                    "valueString": {
                        "locale": "fr",
                        "content": "G729-PORTES COULISSANTES"
                    },
                    "attrUsage": 2,
                    "attrSequence": 0
                },
                {
                    "attrIdentifier": "ATD-UniverCDG",
                    "valueString": {
                        "locale": "fr",
                        "content": "G2-INTERIEUR"
                    },
                    "attrUsage": 2,
                    "attrSequence": 0
                },
                {
                    "attrIdentifier": "ATDDiffusionWebLive",
                    "attrUsage": 2,
                    "valueDecimal": {
                        "locale": "fr",
                        "content": 1
                    },
                    "attrSequence": 0
                },
                {
                    "attrIdentifier": "ATDDiffusionWebWork",
                    "attrUsage": 2,
                    "valueDecimal": {
                        "locale": "fr",
                        "content": 1
                    },
                    "attrSequence": 0
                },
                {
                    "attrIdentifier": "ATDProductPath",
                    "valueString": {
                        "locale": "fr",
                        "content": "G2/G17/G729/G3876/G13166/"
                    },
                    "attrUsage": 2,
                    "attrSequence": 0
                },
                {
                    "attrIdentifier": "ATS-CodeADA",
                    "attrUsage": 2,
                    "valueDecimal": {
                        "locale": "fr",
                        "content": 2550910
                    },
                    "attrSequence": 0
                },
                {
                    "valueIdentifier": "FRA-fr",
                    "attrIdentifier": "ATS-CurrentContextID",
                    "valueString": {
                        "locale": "fr",
                        "content": "RESEAU_FRANCE"
                    },
                    "attrUsage": 2,
                    "attrSequence": 0
                },
                {
                    "valueIdentifier": "CCU0004-ATC-COULEUR-DG2",
                    "attrIdentifier": "CCU0004-ATC-COULEUR",
                    "valueString": {
                        "locale": "fr",
                        "content": "Chêne plaqué brut"
                    },
                    "attrUsage": 2,
                    "attrSequence": 0
                },
                {
                    "valueIdentifier": "CCU0004-ATC-EPAISSEUR-PORTE-40",
                    "attrIdentifier": "CCU0004-ATC-EPAISSEUR-PORTE",
                    "attrUsage": 2,
                    "valueDecimal": {
                        "locale": "fr",
                        "content": 40
                    },
                    "attrSequence": 0
                },
                {
                    "valueIdentifier": "CCU0004-ATC-FINITION-G04",
                    "attrIdentifier": "CCU0004-ATC-FINITION",
                    "valueString": {
                        "locale": "fr",
                        "content": "Décor structuré"
                    },
                    "attrUsage": 2,
                    "attrSequence": 0
                },
                {
                    "valueIdentifier": "CCU0004-ATC-MATERIAU-222",
                    "attrIdentifier": "CCU0004-ATC-MATERIAU",
                    "valueString": {
                        "locale": "fr",
                        "content": "Mdf"
                    },
                    "attrUsage": 2,
                    "attrSequence": 0
                },
                {
                    "valueIdentifier": "CCU0004-ATC-NB-VANTAUX-1",
                    "attrIdentifier": "CCU0004-ATC-NB-VANTAUX",
                    "attrUsage": 2,
                    "valueDecimal": {
                        "locale": "fr",
                        "content": 1
                    },
                    "attrSequence": 0
                },
                {
                    "valueIdentifier": "CCU0004-COMMUNES-3-COMM-ASPECT-CL4",
                    "attrIdentifier": "CCU0004-COMMUNES-3-COMM-ASPECT",
                    "valueString": {
                        "locale": "fr",
                        "content": "Structuré"
                    },
                    "attrUsage": 2,
                    "attrSequence": 0
                },
                {
                    "valueIdentifier": "CCU0004-COMMUNES-3-COMM-TYPE-MATERIAU-015",
                    "attrIdentifier": "CCU0004-COMMUNES-3-COMM-TYPE-MATERIAU",
                    "valueString": {
                        "locale": "fr",
                        "content": "Bois"
                    },
                    "attrUsage": 2,
                    "attrSequence": 0
                },
                {
                    "valueIdentifier": "CCU0004-DIMENSIONS-COMMUNES-DIM-HAUTEUR-204",
                    "attrIdentifier": "CCU0004-DIMENSIONS-COMMUNES-DIM-HAUTEUR",
                    "attrUsage": 2,
                    "valueDecimal": {
                        "locale": "fr",
                        "content": 204
                    },
                    "attrSequence": 0
                },
                {
                    "valueIdentifier": "CCU0004-DIMENSIONS-COMMUNES-DIM-LARGEUR-73",
                    "attrIdentifier": "CCU0004-DIMENSIONS-COMMUNES-DIM-LARGEUR",
                    "attrUsage": 1,
                    "valueDecimal": {
                        "locale": "fr",
                        "content": 73
                    },
                    "attrSequence": 0
                },
                {
                    "valueIdentifier": "CCU0004-DIMENSIONS-COMMUNES-DIM-POIDS-21",
                    "attrIdentifier": "CCU0004-DIMENSIONS-COMMUNES-DIM-POIDS",
                    "attrUsage": 2,
                    "valueDecimal": {
                        "locale": "fr",
                        "content": 21
                    },
                    "attrSequence": 0
                },
                {
                    "valueIdentifier": "CCU0004-DIMENSIONS-COMMUNES-DIM-PROFONDEUR-9",
                    "attrIdentifier": "CCU0004-DIMENSIONS-COMMUNES-DIM-PROFONDEUR",
                    "attrUsage": 2,
                    "valueDecimal": {
                        "locale": "fr",
                        "content": 9
                    },
                    "attrSequence": 0
                },
                {
                    "attrIdentifier": "COMMUNE-COMM-ART-ETQ-LS",
                    "attrUsage": 2,
                    "valueDecimal": {
                        "locale": "fr",
                        "content": 0
                    },
                    "attrSequence": 0
                },
                {
                    "valueIdentifier": "ART",
                    "attrIdentifier": "COMMUNE-COMM-ART-TYP-TARIF",
                    "valueString": {
                        "locale": "fr",
                        "content": "PRIX DEFINI"
                    },
                    "attrUsage": 2,
                    "attrSequence": 0
                },
                {
                    "valueIdentifier": "ORD",
                    "attrIdentifier": "COMMUNE-COMM-ART-TYPE",
                    "valueString": {
                        "locale": "fr",
                        "content": "ORDINAIRE"
                    },
                    "attrUsage": 2,
                    "attrSequence": 0
                },
                {
                    "valueIdentifier": "SO",
                    "attrIdentifier": "COMMUNE-SUITE-COMM-ART-DUREE-VIE",
                    "valueString": {
                        "locale": "fr",
                        "content": "SANS OBJET"
                    },
                    "attrUsage": 2,
                    "attrSequence": 0
                },
                {
                    "attrIdentifier": "COMMUNE-SUITE-COMM-ART-INFLAMMABLE",
                    "attrUsage": 2,
                    "valueDecimal": {
                        "locale": "fr",
                        "content": 0
                    },
                    "attrSequence": 0
                },
                {
                    "valueIdentifier": "CDG",
                    "attrIdentifier": "COMMUNE-SUITE-SPEC-NAT-NIVEAU",
                    "valueString": {
                        "locale": "fr",
                        "content": "Coeur De Gamme"
                    },
                    "attrUsage": 2,
                    "attrSequence": 0
                },
                {
                    "valueIdentifier": "CTP",
                    "attrIdentifier": "COMMUNE-SUITE-SPEC-NAT-STYLE",
                    "valueString": {
                        "locale": "fr",
                        "content": "Contemporain"
                    },
                    "attrUsage": 2,
                    "attrSequence": 0
                },
                {
                    "attrIdentifier": "COMMUNES-3-ACHAT-LOCAL",
                    "attrUsage": 2,
                    "valueDecimal": {
                        "locale": "fr",
                        "content": 0
                    },
                    "attrSequence": 0
                },
                {
                    "attrIdentifier": "COMMUNES-3-COMM-ADAP-DIM",
                    "attrUsage": 2,
                    "valueDecimal": {
                        "locale": "fr",
                        "content": 0
                    },
                    "attrSequence": 0
                },
                {
                    "attrIdentifier": "COMMUNES-3-COMM-ART-EXCLUS-VERI",
                    "attrUsage": 2,
                    "valueDecimal": {
                        "locale": "fr",
                        "content": 0
                    },
                    "attrSequence": 0
                },
                {
                    "attrIdentifier": "COMMUNES-3-COMM-COEF-VOL",
                    "attrUsage": 2,
                    "valueDecimal": {
                        "locale": "fr",
                        "content": 1
                    },
                    "attrSequence": 0
                },
                {
                    "attrIdentifier": "COMMUNES-3-COMM-DIFFUSION-WEB",
                    "attrUsage": 2,
                    "valueDecimal": {
                        "locale": "fr",
                        "content": 1
                    },
                    "attrSequence": 0
                },
                {
                    "attrIdentifier": "COMMUNES-3-COMM-GARANTIE",
                    "valueString": {
                        "locale": "fr",
                        "content": "2 ans"
                    },
                    "attrUsage": 2,
                    "attrSequence": 0
                },
                {
                    "attrIdentifier": "COMMUNES-3-COMM-RENO-PLUS",
                    "attrUsage": 2,
                    "valueDecimal": {
                        "locale": "fr",
                        "content": 0
                    },
                    "attrSequence": 0
                },
                {
                    "valueIdentifier": "004",
                    "attrIdentifier": "COMMUNES-3-COMM-STD-SM-STDOPT",
                    "valueString": {
                        "locale": "fr",
                        "content": "Standard"
                    },
                    "attrUsage": 2,
                    "attrSequence": 0
                },
                {
                    "valueIdentifier": "001",
                    "attrIdentifier": "COMMUNES-3-COMM-TYPE-PDT",
                    "valueString": {
                        "locale": "fr",
                        "content": "Principal"
                    },
                    "attrUsage": 2,
                    "attrSequence": 0
                },
                {
                    "attrIdentifier": "DIMENSIONS-COMMUNES-DIM-HAUTEUR-EMB",
                    "attrUsage": 2,
                    "valueDecimal": {
                        "locale": "fr",
                        "content": 205
                    },
                    "attrSequence": 0
                },
                {
                    "attrIdentifier": "DIMENSIONS-COMMUNES-DIM-LARGEUR-EMB",
                    "attrUsage": 2,
                    "valueDecimal": {
                        "locale": "fr",
                        "content": 74
                    },
                    "attrSequence": 0
                },
                {
                    "attrIdentifier": "DIMENSIONS-COMMUNES-DIM-PROFONDEUR-EMB",
                    "attrUsage": 2,
                    "valueDecimal": {
                        "locale": "fr",
                        "content": 5
                    },
                    "attrSequence": 0
                },
                {
                    "attrIdentifier": "DIMENSIONS-COMMUNES-DIM-VOLUME",
                    "attrUsage": 2,
                    "valueDecimal": {
                        "locale": "fr",
                        "content": 134.028
                    },
                    "attrSequence": 0
                },
                {
                    "attrIdentifier": "IS-ELIGIBLE-PROMO-SIMPLE",
                    "valueString": {
                        "locale": "fr",
                        "content": "NON"
                    },
                    "attrUsage": 2,
                    "attrSequence": 0
                },
                {
                    "attrIdentifier": "RESEAU-DISTRIBUTION-RESEAU-ANTILLES",
                    "attrUsage": 2,
                    "valueDecimal": {
                        "locale": "fr",
                        "content": 1
                    },
                    "attrSequence": 0
                },
                {
                    "attrIdentifier": "RESEAU-DISTRIBUTION-RESEAU-PLATEFORME",
                    "attrUsage": 2,
                    "valueDecimal": {
                        "locale": "fr",
                        "content": 0
                    },
                    "attrSequence": 0
                },
                {
                    "attrIdentifier": "RESEAU-DISTRIBUTION-RESEAU-REUNION",
                    "attrUsage": 2,
                    "valueDecimal": {
                        "locale": "fr",
                        "content": 1
                    },
                    "attrSequence": 0
                },
                {
                    "attrIdentifier": "RESEAU-DISTRIBUTION-RESEAU-SUISSE",
                    "attrUsage": 2,
                    "valueDecimal": {
                        "locale": "fr",
                        "content": 1
                    },
                    "attrSequence": 0
                },
                {
                    "valueIdentifier": 164,
                    "attrIdentifier": "SPEC-FAM-CHX",
                    "valueString": {
                        "locale": "fr",
                        "content": "PLEIN"
                    },
                    "attrUsage": 2,
                    "attrSequence": 0
                },
                {
                    "valueIdentifier": 687,
                    "attrIdentifier": "SPEC-FAM-CMA",
                    "valueString": {
                        "locale": "fr",
                        "content": "RIVE DROITE"
                    },
                    "attrUsage": 2,
                    "attrSequence": 0
                },
                {
                    "valueIdentifier": 230,
                    "attrIdentifier": "SPEC-FAM-DET",
                    "valueString": {
                        "locale": "fr",
                        "content": "UN VANTAIL"
                    },
                    "attrUsage": 2,
                    "attrSequence": 0
                },
                {
                    "valueIdentifier": 379,
                    "attrIdentifier": "SPEC-FAM-GAM",
                    "valueString": {
                        "locale": "fr",
                        "content": "MENUISEE"
                    },
                    "attrUsage": 2,
                    "attrSequence": 0
                },
                {
                    "valueIdentifier": 115,
                    "attrIdentifier": "SPEC-FAM-MDE",
                    "valueString": {
                        "locale": "fr",
                        "content": "STANDARD"
                    },
                    "attrUsage": 2,
                    "attrSequence": 0
                },
                {
                    "valueIdentifier": "R95",
                    "attrIdentifier": "SPEC-FAM-NMA",
                    "valueString": {
                        "locale": "fr",
                        "content": "CHENE PLAQUE"
                    },
                    "attrUsage": 2,
                    "attrSequence": 0
                },
                {
                    "valueIdentifier": 1,
                    "attrIdentifier": "SPECIF-RESO-XXX-SPEC-RESO-CATAL-TYPE",
                    "valueString": {
                        "locale": "fr",
                        "content": "MENUISERIES"
                    },
                    "attrUsage": 2,
                    "attrSequence": 0
                },
                {
                    "attrIdentifier": "SPECIF-RESO-XXX-SPEC-RESO-DEG",
                    "attrUsage": 2,
                    "valueDecimal": {
                        "locale": "fr",
                        "content": 0
                    },
                    "attrSequence": 0
                },
                {
                    "attrIdentifier": "SPECIF-RESO-XXX-SPEC-RESO-ENV-DEPOT",
                    "attrUsage": 2,
                    "valueDecimal": {
                        "locale": "fr",
                        "content": 1
                    },
                    "attrSequence": 0
                },
                {
                    "valueIdentifier": 0,
                    "attrIdentifier": "SPECIF-RESO-XXX-SPEC-RESO-OBSO",
                    "valueString": {
                        "locale": "fr",
                        "content": "A l'offre"
                    },
                    "attrUsage": 2,
                    "attrSequence": 0
                },
                {
                    "attrIdentifier": "SPECIF-RESO-XXX-SPEC-RESO-REMISE",
                    "attrUsage": 2,
                    "valueDecimal": {
                        "locale": "fr",
                        "content": 1
                    },
                    "attrSequence": 0
                },
                {
                    "valueIdentifier": 1,
                    "attrIdentifier": "SPECIF-RESO-XXX-SPEC-RESO-TVA",
                    "valueString": {
                        "locale": "fr",
                        "content": "20 %"
                    },
                    "attrUsage": 2,
                    "attrSequence": 0
                },
                {
                    "valueIdentifier": 3,
                    "attrIdentifier": "SPECIF-RESO-XXX-SPEC-RESO-TVA2",
                    "valueString": {
                        "locale": "fr",
                        "content": "10% (Pose)"
                    },
                    "attrUsage": 2,
                    "attrSequence": 0
                },
                {
                    "attrIdentifier": "categorieGoogle",
                    "valueString": {
                        "locale": "fr",
                        "content": 119
                    },
                    "attrUsage": 2,
                    "attrSequence": 0
                },
                {
                    "attrIdentifier": "colissimo",
                    "attrUsage": 2,
                    "valueDecimal": {
                        "locale": "fr",
                        "content": 0
                    },
                    "attrSequence": 0
                },
                {
                    "valueIdentifier": 0,
                    "attrIdentifier": "contrainteColisage",
                    "valueString": {
                        "locale": "fr",
                        "content": 0
                    },
                    "attrUsage": 2,
                    "attrSequence": 0
                },
                {
                    "attrIdentifier": "isLivraisonDirecte",
                    "attrUsage": 2,
                    "valueDecimal": {
                        "locale": "fr",
                        "content": 0
                    },
                    "attrSequence": 0
                },
                {
                    "attrIdentifier": "poids",
                    "attrUsage": 2,
                    "valueDecimal": {
                        "locale": "fr",
                        "content": 21.31
                    },
                    "attrSequence": 0
                },
                {
                    "attrIdentifier": "priceLabel",
                    "valueString": {
                        "locale": "fr",
                        "content": "Prix pour la dimension H 204 x L 73 cm"
                    },
                    "attrUsage": 2,
                    "attrSequence": 0
                },
                {
                    "valueIdentifier": "UN",
                    "attrIdentifier": "uniteSecondaire",
                    "valueString": {
                        "locale": "fr",
                        "content": "UN"
                    },
                    "attrUsage": 2,
                    "attrSequence": 0
                },
                {
                    "valueIdentifier": "UN",
                    "attrIdentifier": "uniteVente",
                    "valueString": {
                        "locale": "fr",
                        "content": "UN"
                    },
                    "attrUsage": 2,
                    "attrSequence": 0
                },
                {
                    "valueIdentifier": "UN",
                    "attrIdentifier": "uniteVenteLegale",
                    "valueString": {
                        "locale": "fr",
                        "content": "UN"
                    },
                    "attrUsage": 2,
                    "attrSequence": 0
                }
            ]},
            "isDefault": true,
            "seoItem": {"urlKeyword": {
                "locale": "fr",
                "content": "porte-coulissante-quadral-4-panneaux-plaques-chene-h-204-x-l-73-cm-2550910"
            }},
            "imageFull": {"locale": "fr"},
            "shortDesc": {"locale": "fr"},
            "published": {
                "locale": "fr",
                "content": false
            },
            "label": {
                "locale": "fr",
                "content": "Porte coulissante QUADRAL 4 panneaux plaqués chêne H.204 x l.73 cm"
            },
            "sku": 2550910,
            "additionalDesc1": {"locale": "fr"},
            "longDesc": {
                "locale": "fr",
                "content": "- Produit : Porte coulissante <BR/>- Modèle : Quadral 4 panneaux<BR/>- Type de porte : chêne plaqué<BR/>- Type de chant : rive droite<BR/>- Composition : Panneaux en aggloméré revêtu d'un placage chêne  1er choix à vernir<BR/>- Montants et traverses en MDF ou aggloméré plaqué chêne<BR/>- Finition : incolore sur demande en magasin<BR/>- Hauteur de porte : 204 cm<BR/>- Largeur de porte : 73, 83, 93 cm<BR/>- Epaisseur de porte : 40mm<BR/>- Serrure magnétique à clé<BR/>- Poignée : non comprise, trou poignée et tire-doigt usinée<BR/>- Recoupable : non<BR/>- La pose sur cloison humide (exemples : carreaux de plâtre, briques + plâtre) doit se faire en priorité sur huisserie fin de chantier avec utilisation d\u2019un précadre. S'il n\u2019y a pas d\u2019huisserie fin de chantier, alors appliquer un bouche pore sur le bout du poteau pour éviter les remontées d\u2019humidité, et sur la feuillure en contact avec la cloison humide."
            },
            "additionalDesc2": {"locale": "fr"},
            "imageThumbnail": {"locale": "fr"}
        },
        {
            "attributeValueList": {"attributeValue": [
                {
                    "attrIdentifier": "ATC-AUSSI-SUR-MESURE",
                    "attrUsage": 2,
                    "valueDecimal": {
                        "locale": "fr",
                        "content": 0
                    },
                    "attrSequence": 0
                },
                {
                    "valueIdentifier": "K61",
                    "attrIdentifier": "ATC-CHANT",
                    "valueString": {
                        "locale": "fr",
                        "content": "Rive droite"
                    },
                    "attrUsage": 2,
                    "attrSequence": 0
                },
                {
                    "attrIdentifier": "ATC-COULEUR-CARTE",
                    "attrUsage": 2,
                    "valueDecimal": {
                        "locale": "fr",
                        "content": 0
                    },
                    "attrSequence": 0
                },
                {
                    "attrIdentifier": "ATC-FAB-EN-FRANCE",
                    "attrUsage": 2,
                    "valueDecimal": {
                        "locale": "fr",
                        "content": 0
                    },
                    "attrSequence": 0
                },
                {
                    "attrIdentifier": "ATC-FAB-PAR-LAPEYRE",
                    "attrUsage": 2,
                    "valueDecimal": {
                        "locale": "fr",
                        "content": 0
                    },
                    "attrSequence": 0
                },
                {
                    "valueIdentifier": "V47",
                    "attrIdentifier": "ATC-GAMME-SPECIFIQUE",
                    "valueString": {
                        "locale": "fr",
                        "content": "Portes intérieures"
                    },
                    "attrUsage": 2,
                    "attrSequence": 0
                },
                {
                    "attrIdentifier": "ATC-HAUTEUR-TOTALE",
                    "attrUsage": 2,
                    "valueDecimal": {
                        "locale": "fr",
                        "content": 204
                    },
                    "attrSequence": 0
                },
                {
                    "attrIdentifier": "ATC-LARGEUR-PASSAGE",
                    "attrUsage": 2,
                    "valueDecimal": {
                        "locale": "fr",
                        "content": 81.4
                    },
                    "attrSequence": 0
                },
                {
                    "attrIdentifier": "ATC-LARGEUR-TOTALE",
                    "attrUsage": 2,
                    "valueDecimal": {
                        "locale": "fr",
                        "content": 83
                    },
                    "attrSequence": 0
                },
                {
                    "attrIdentifier": "ATC-NORME-FSC",
                    "attrUsage": 2,
                    "valueDecimal": {
                        "locale": "fr",
                        "content": 0
                    },
                    "attrSequence": 0
                },
                {
                    "attrIdentifier": "ATC-NORME-PEFC",
                    "attrUsage": 2,
                    "valueDecimal": {
                        "locale": "fr",
                        "content": 0
                    },
                    "attrSequence": 0
                },
                {
                    "valueIdentifier": "K31",
                    "attrIdentifier": "ATC-PRODUIT",
                    "valueString": {
                        "locale": "fr",
                        "content": "Porte coulissante"
                    },
                    "attrUsage": 2,
                    "attrSequence": 0
                },
                {
                    "attrIdentifier": "ATD-CategorieCDG",
                    "valueString": {
                        "locale": "fr",
                        "content": "G3876-PORTES CHENE PLAQUE"
                    },
                    "attrUsage": 2,
                    "attrSequence": 0
                },
                {
                    "attrIdentifier": "ATD-FamilleCDG",
                    "valueString": {
                        "locale": "fr",
                        "content": "G17-PORTES INTERIEURES"
                    },
                    "attrUsage": 2,
                    "attrSequence": 0
                },
                {
                    "attrIdentifier": "ATD-LibelleCommercial",
                    "valueString": {
                        "locale": "fr",
                        "content": "Porte coulissante QUADRAL 4 panneaux plaqués chêne H.204 x l.83 cm"
                    },
                    "attrUsage": 2,
                    "attrSequence": 0
                },
                {
                    "attrIdentifier": "ATD-SousCategorieCDG",
                    "valueString": {
                        "locale": "fr",
                        "content": "G13166-QUADRAL PLEIN"
                    },
                    "attrUsage": 2,
                    "attrSequence": 0
                },
                {
                    "attrIdentifier": "ATD-SousCategorieCDG2",
                    "valueString": {
                        "locale": "fr",
                        "content": "2550920-PS COUL QUADRAL 4 PANNEAUX 204X83"
                    },
                    "attrUsage": 2,
                    "attrSequence": 0
                },
                {
                    "attrIdentifier": "ATD-SousCategorieCDG3",
                    "valueString": {
                        "locale": "fr",
                        "content": "N/A"
                    },
                    "attrUsage": 2,
                    "attrSequence": 0
                },
                {
                    "attrIdentifier": "ATD-SousFamilleCDG",
                    "valueString": {
                        "locale": "fr",
                        "content": "G729-PORTES COULISSANTES"
                    },
                    "attrUsage": 2,
                    "attrSequence": 0
                },
                {
                    "attrIdentifier": "ATD-UniverCDG",
                    "valueString": {
                        "locale": "fr",
                        "content": "G2-INTERIEUR"
                    },
                    "attrUsage": 2,
                    "attrSequence": 0
                },
                {
                    "attrIdentifier": "ATDDiffusionWebLive",
                    "attrUsage": 2,
                    "valueDecimal": {
                        "locale": "fr",
                        "content": 1
                    },
                    "attrSequence": 0
                },
                {
                    "attrIdentifier": "ATDDiffusionWebWork",
                    "attrUsage": 2,
                    "valueDecimal": {
                        "locale": "fr",
                        "content": 1
                    },
                    "attrSequence": 0
                },
                {
                    "attrIdentifier": "ATDProductPath",
                    "valueString": {
                        "locale": "fr",
                        "content": "G2/G17/G729/G3876/G13166/"
                    },
                    "attrUsage": 2,
                    "attrSequence": 0
                },
                {
                    "attrIdentifier": "ATS-CodeADA",
                    "attrUsage": 2,
                    "valueDecimal": {
                        "locale": "fr",
                        "content": 2550920
                    },
                    "attrSequence": 0
                },
                {
                    "valueIdentifier": "FRA-fr",
                    "attrIdentifier": "ATS-CurrentContextID",
                    "valueString": {
                        "locale": "fr",
                        "content": "RESEAU_FRANCE"
                    },
                    "attrUsage": 2,
                    "attrSequence": 0
                },
                {
                    "valueIdentifier": "CCU0004-ATC-COULEUR-DG2",
                    "attrIdentifier": "CCU0004-ATC-COULEUR",
                    "valueString": {
                        "locale": "fr",
                        "content": "Chêne plaqué brut"
                    },
                    "attrUsage": 2,
                    "attrSequence": 0
                },
                {
                    "valueIdentifier": "CCU0004-ATC-EPAISSEUR-PORTE-40",
                    "attrIdentifier": "CCU0004-ATC-EPAISSEUR-PORTE",
                    "attrUsage": 2,
                    "valueDecimal": {
                        "locale": "fr",
                        "content": 40
                    },
                    "attrSequence": 0
                },
                {
                    "valueIdentifier": "CCU0004-ATC-FINITION-G04",
                    "attrIdentifier": "CCU0004-ATC-FINITION",
                    "valueString": {
                        "locale": "fr",
                        "content": "Décor structuré"
                    },
                    "attrUsage": 2,
                    "attrSequence": 0
                },
                {
                    "valueIdentifier": "CCU0004-ATC-MATERIAU-222",
                    "attrIdentifier": "CCU0004-ATC-MATERIAU",
                    "valueString": {
                        "locale": "fr",
                        "content": "Mdf"
                    },
                    "attrUsage": 2,
                    "attrSequence": 0
                },
                {
                    "valueIdentifier": "CCU0004-ATC-NB-VANTAUX-1",
                    "attrIdentifier": "CCU0004-ATC-NB-VANTAUX",
                    "attrUsage": 2,
                    "valueDecimal": {
                        "locale": "fr",
                        "content": 1
                    },
                    "attrSequence": 0
                },
                {
                    "valueIdentifier": "CCU0004-COMMUNES-3-COMM-ASPECT-CL4",
                    "attrIdentifier": "CCU0004-COMMUNES-3-COMM-ASPECT",
                    "valueString": {
                        "locale": "fr",
                        "content": "Structuré"
                    },
                    "attrUsage": 2,
                    "attrSequence": 0
                },
                {
                    "valueIdentifier": "CCU0004-COMMUNES-3-COMM-TYPE-MATERIAU-015",
                    "attrIdentifier": "CCU0004-COMMUNES-3-COMM-TYPE-MATERIAU",
                    "valueString": {
                        "locale": "fr",
                        "content": "Bois"
                    },
                    "attrUsage": 2,
                    "attrSequence": 0
                },
                {
                    "valueIdentifier": "CCU0004-DIMENSIONS-COMMUNES-DIM-HAUTEUR-204",
                    "attrIdentifier": "CCU0004-DIMENSIONS-COMMUNES-DIM-HAUTEUR",
                    "attrUsage": 2,
                    "valueDecimal": {
                        "locale": "fr",
                        "content": 204
                    },
                    "attrSequence": 0
                },
                {
                    "valueIdentifier": "CCU0004-DIMENSIONS-COMMUNES-DIM-LARGEUR-83",
                    "attrIdentifier": "CCU0004-DIMENSIONS-COMMUNES-DIM-LARGEUR",
                    "attrUsage": 1,
                    "valueDecimal": {
                        "locale": "fr",
                        "content": 83
                    },
                    "attrSequence": 0
                },
                {
                    "valueIdentifier": "CCU0004-DIMENSIONS-COMMUNES-DIM-POIDS-20.6",
                    "attrIdentifier": "CCU0004-DIMENSIONS-COMMUNES-DIM-POIDS",
                    "attrUsage": 2,
                    "valueDecimal": {
                        "locale": "fr",
                        "content": 20.6
                    },
                    "attrSequence": 0
                },
                {
                    "valueIdentifier": "CCU0004-DIMENSIONS-COMMUNES-DIM-PROFONDEUR-9",
                    "attrIdentifier": "CCU0004-DIMENSIONS-COMMUNES-DIM-PROFONDEUR",
                    "attrUsage": 2,
                    "valueDecimal": {
                        "locale": "fr",
                        "content": 9
                    },
                    "attrSequence": 0
                },
                {
                    "attrIdentifier": "COMMUNE-COMM-ART-ETQ-LS",
                    "attrUsage": 2,
                    "valueDecimal": {
                        "locale": "fr",
                        "content": 0
                    },
                    "attrSequence": 0
                },
                {
                    "valueIdentifier": "ART",
                    "attrIdentifier": "COMMUNE-COMM-ART-TYP-TARIF",
                    "valueString": {
                        "locale": "fr",
                        "content": "PRIX DEFINI"
                    },
                    "attrUsage": 2,
                    "attrSequence": 0
                },
                {
                    "valueIdentifier": "ORD",
                    "attrIdentifier": "COMMUNE-COMM-ART-TYPE",
                    "valueString": {
                        "locale": "fr",
                        "content": "ORDINAIRE"
                    },
                    "attrUsage": 2,
                    "attrSequence": 0
                },
                {
                    "valueIdentifier": "SO",
                    "attrIdentifier": "COMMUNE-SUITE-COMM-ART-DUREE-VIE",
                    "valueString": {
                        "locale": "fr",
                        "content": "SANS OBJET"
                    },
                    "attrUsage": 2,
                    "attrSequence": 0
                },
                {
                    "attrIdentifier": "COMMUNE-SUITE-COMM-ART-INFLAMMABLE",
                    "attrUsage": 2,
                    "valueDecimal": {
                        "locale": "fr",
                        "content": 0
                    },
                    "attrSequence": 0
                },
                {
                    "valueIdentifier": "CDG",
                    "attrIdentifier": "COMMUNE-SUITE-SPEC-NAT-NIVEAU",
                    "valueString": {
                        "locale": "fr",
                        "content": "Coeur De Gamme"
                    },
                    "attrUsage": 2,
                    "attrSequence": 0
                },
                {
                    "valueIdentifier": "CTP",
                    "attrIdentifier": "COMMUNE-SUITE-SPEC-NAT-STYLE",
                    "valueString": {
                        "locale": "fr",
                        "content": "Contemporain"
                    },
                    "attrUsage": 2,
                    "attrSequence": 0
                },
                {
                    "attrIdentifier": "COMMUNES-3-ACHAT-LOCAL",
                    "attrUsage": 2,
                    "valueDecimal": {
                        "locale": "fr",
                        "content": 0
                    },
                    "attrSequence": 0
                },
                {
                    "attrIdentifier": "COMMUNES-3-COMM-ADAP-DIM",
                    "attrUsage": 2,
                    "valueDecimal": {
                        "locale": "fr",
                        "content": 0
                    },
                    "attrSequence": 0
                },
                {
                    "attrIdentifier": "COMMUNES-3-COMM-ART-EXCLUS-VERI",
                    "attrUsage": 2,
                    "valueDecimal": {
                        "locale": "fr",
                        "content": 0
                    },
                    "attrSequence": 0
                },
                {
                    "attrIdentifier": "COMMUNES-3-COMM-COEF-VOL",
                    "attrUsage": 2,
                    "valueDecimal": {
                        "locale": "fr",
                        "content": 1
                    },
                    "attrSequence": 0
                },
                {
                    "attrIdentifier": "COMMUNES-3-COMM-DIFFUSION-WEB",
                    "attrUsage": 2,
                    "valueDecimal": {
                        "locale": "fr",
                        "content": 1
                    },
                    "attrSequence": 0
                },
                {
                    "attrIdentifier": "COMMUNES-3-COMM-GARANTIE",
                    "valueString": {
                        "locale": "fr",
                        "content": "2 ans"
                    },
                    "attrUsage": 2,
                    "attrSequence": 0
                },
                {
                    "attrIdentifier": "COMMUNES-3-COMM-RENO-PLUS",
                    "attrUsage": 2,
                    "valueDecimal": {
                        "locale": "fr",
                        "content": 0
                    },
                    "attrSequence": 0
                },
                {
                    "valueIdentifier": "004",
                    "attrIdentifier": "COMMUNES-3-COMM-STD-SM-STDOPT",
                    "valueString": {
                        "locale": "fr",
                        "content": "Standard"
                    },
                    "attrUsage": 2,
                    "attrSequence": 0
                },
                {
                    "valueIdentifier": "001",
                    "attrIdentifier": "COMMUNES-3-COMM-TYPE-PDT",
                    "valueString": {
                        "locale": "fr",
                        "content": "Principal"
                    },
                    "attrUsage": 2,
                    "attrSequence": 0
                },
                {
                    "attrIdentifier": "DIMENSIONS-COMMUNES-DIM-HAUTEUR-EMB",
                    "attrUsage": 2,
                    "valueDecimal": {
                        "locale": "fr",
                        "content": 205
                    },
                    "attrSequence": 0
                },
                {
                    "attrIdentifier": "DIMENSIONS-COMMUNES-DIM-LARGEUR-EMB",
                    "attrUsage": 2,
                    "valueDecimal": {
                        "locale": "fr",
                        "content": 84
                    },
                    "attrSequence": 0
                },
                {
                    "attrIdentifier": "DIMENSIONS-COMMUNES-DIM-PROFONDEUR-EMB",
                    "attrUsage": 2,
                    "valueDecimal": {
                        "locale": "fr",
                        "content": 5
                    },
                    "attrSequence": 0
                },
                {
                    "attrIdentifier": "DIMENSIONS-COMMUNES-DIM-VOLUME",
                    "attrUsage": 2,
                    "valueDecimal": {
                        "locale": "fr",
                        "content": 152.388
                    },
                    "attrSequence": 0
                },
                {
                    "attrIdentifier": "IS-ELIGIBLE-PROMO-SIMPLE",
                    "valueString": {
                        "locale": "fr",
                        "content": "NON"
                    },
                    "attrUsage": 2,
                    "attrSequence": 0
                },
                {
                    "attrIdentifier": "RESEAU-DISTRIBUTION-RESEAU-ANTILLES",
                    "attrUsage": 2,
                    "valueDecimal": {
                        "locale": "fr",
                        "content": 1
                    },
                    "attrSequence": 0
                },
                {
                    "attrIdentifier": "RESEAU-DISTRIBUTION-RESEAU-PLATEFORME",
                    "attrUsage": 2,
                    "valueDecimal": {
                        "locale": "fr",
                        "content": 0
                    },
                    "attrSequence": 0
                },
                {
                    "attrIdentifier": "RESEAU-DISTRIBUTION-RESEAU-REUNION",
                    "attrUsage": 2,
                    "valueDecimal": {
                        "locale": "fr",
                        "content": 1
                    },
                    "attrSequence": 0
                },
                {
                    "attrIdentifier": "RESEAU-DISTRIBUTION-RESEAU-SUISSE",
                    "attrUsage": 2,
                    "valueDecimal": {
                        "locale": "fr",
                        "content": 1
                    },
                    "attrSequence": 0
                },
                {
                    "valueIdentifier": 164,
                    "attrIdentifier": "SPEC-FAM-CHX",
                    "valueString": {
                        "locale": "fr",
                        "content": "PLEIN"
                    },
                    "attrUsage": 2,
                    "attrSequence": 0
                },
                {
                    "valueIdentifier": 687,
                    "attrIdentifier": "SPEC-FAM-CMA",
                    "valueString": {
                        "locale": "fr",
                        "content": "RIVE DROITE"
                    },
                    "attrUsage": 2,
                    "attrSequence": 0
                },
                {
                    "valueIdentifier": 230,
                    "attrIdentifier": "SPEC-FAM-DET",
                    "valueString": {
                        "locale": "fr",
                        "content": "UN VANTAIL"
                    },
                    "attrUsage": 2,
                    "attrSequence": 0
                },
                {
                    "valueIdentifier": 379,
                    "attrIdentifier": "SPEC-FAM-GAM",
                    "valueString": {
                        "locale": "fr",
                        "content": "MENUISEE"
                    },
                    "attrUsage": 2,
                    "attrSequence": 0
                },
                {
                    "valueIdentifier": 115,
                    "attrIdentifier": "SPEC-FAM-MDE",
                    "valueString": {
                        "locale": "fr",
                        "content": "STANDARD"
                    },
                    "attrUsage": 2,
                    "attrSequence": 0
                },
                {
                    "valueIdentifier": "R95",
                    "attrIdentifier": "SPEC-FAM-NMA",
                    "valueString": {
                        "locale": "fr",
                        "content": "CHENE PLAQUE"
                    },
                    "attrUsage": 2,
                    "attrSequence": 0
                },
                {
                    "valueIdentifier": 1,
                    "attrIdentifier": "SPECIF-RESO-XXX-SPEC-RESO-CATAL-TYPE",
                    "valueString": {
                        "locale": "fr",
                        "content": "MENUISERIES"
                    },
                    "attrUsage": 2,
                    "attrSequence": 0
                },
                {
                    "attrIdentifier": "SPECIF-RESO-XXX-SPEC-RESO-DEG",
                    "attrUsage": 2,
                    "valueDecimal": {
                        "locale": "fr",
                        "content": 0
                    },
                    "attrSequence": 0
                },
                {
                    "attrIdentifier": "SPECIF-RESO-XXX-SPEC-RESO-ENV-DEPOT",
                    "attrUsage": 2,
                    "valueDecimal": {
                        "locale": "fr",
                        "content": 1
                    },
                    "attrSequence": 0
                },
                {
                    "valueIdentifier": 0,
                    "attrIdentifier": "SPECIF-RESO-XXX-SPEC-RESO-OBSO",
                    "valueString": {
                        "locale": "fr",
                        "content": "A l'offre"
                    },
                    "attrUsage": 2,
                    "attrSequence": 0
                },
                {
                    "attrIdentifier": "SPECIF-RESO-XXX-SPEC-RESO-REMISE",
                    "attrUsage": 2,
                    "valueDecimal": {
                        "locale": "fr",
                        "content": 1
                    },
                    "attrSequence": 0
                },
                {
                    "valueIdentifier": 1,
                    "attrIdentifier": "SPECIF-RESO-XXX-SPEC-RESO-TVA",
                    "valueString": {
                        "locale": "fr",
                        "content": "20 %"
                    },
                    "attrUsage": 2,
                    "attrSequence": 0
                },
                {
                    "valueIdentifier": 3,
                    "attrIdentifier": "SPECIF-RESO-XXX-SPEC-RESO-TVA2",
                    "valueString": {
                        "locale": "fr",
                        "content": "10% (Pose)"
                    },
                    "attrUsage": 2,
                    "attrSequence": 0
                },
                {
                    "attrIdentifier": "categorieGoogle",
                    "valueString": {
                        "locale": "fr",
                        "content": 119
                    },
                    "attrUsage": 2,
                    "attrSequence": 0
                },
                {
                    "attrIdentifier": "colissimo",
                    "attrUsage": 2,
                    "valueDecimal": {
                        "locale": "fr",
                        "content": 0
                    },
                    "attrSequence": 0
                },
                {
                    "valueIdentifier": 0,
                    "attrIdentifier": "contrainteColisage",
                    "valueString": {
                        "locale": "fr",
                        "content": 0
                    },
                    "attrUsage": 2,
                    "attrSequence": 0
                },
                {
                    "attrIdentifier": "isLivraisonDirecte",
                    "attrUsage": 2,
                    "valueDecimal": {
                        "locale": "fr",
                        "content": 0
                    },
                    "attrSequence": 0
                },
                {
                    "attrIdentifier": "poids",
                    "attrUsage": 2,
                    "valueDecimal": {
                        "locale": "fr",
                        "content": 20.91
                    },
                    "attrSequence": 0
                },
                {
                    "attrIdentifier": "priceLabel",
                    "valueString": {
                        "locale": "fr",
                        "content": "Prix pour la dimension H 204 x L 83 cm"
                    },
                    "attrUsage": 2,
                    "attrSequence": 0
                },
                {
                    "valueIdentifier": "UN",
                    "attrIdentifier": "uniteSecondaire",
                    "valueString": {
                        "locale": "fr",
                        "content": "UN"
                    },
                    "attrUsage": 2,
                    "attrSequence": 0
                },
                {
                    "valueIdentifier": "UN",
                    "attrIdentifier": "uniteVente",
                    "valueString": {
                        "locale": "fr",
                        "content": "UN"
                    },
                    "attrUsage": 2,
                    "attrSequence": 0
                },
                {
                    "valueIdentifier": "UN",
                    "attrIdentifier": "uniteVenteLegale",
                    "valueString": {
                        "locale": "fr",
                        "content": "UN"
                    },
                    "attrUsage": 2,
                    "attrSequence": 0
                }
            ]},
            "isDefault": false,
            "seoItem": {"urlKeyword": {
                "locale": "fr",
                "content": "porte-coulissante-quadral-4-panneaux-plaques-chene-h-204-x-l-83-cm-2550920"
            }},
            "imageFull": {"locale": "fr"},
            "shortDesc": {"locale": "fr"},
            "published": {
                "locale": "fr",
                "content": false
            },
            "label": {
                "locale": "fr",
                "content": "Porte coulissante QUADRAL 4 panneaux plaqués chêne H.204 x l.83 cm"
            },
            "sku": 2550920,
            "additionalDesc1": {"locale": "fr"},
            "longDesc": {
                "locale": "fr",
                "content": "- Produit : Porte coulissante <BR/>- Modèle : Quadral 4 panneaux<BR/>- Type de porte : chêne plaqué<BR/>- Type de chant : rive droite<BR/>- Composition : Panneaux en aggloméré revêtu d'un placage chêne  1er choix à vernir<BR/>- Montants et traverses en MDF ou aggloméré plaqué chêne<BR/>- Finition : incolore sur demande en magasin<BR/>- Hauteur de porte : 204 cm<BR/>- Largeur de porte : 73, 83, 93 cm<BR/>- Epaisseur de porte : 40mm<BR/>- Serrure magnétique à clé<BR/>- Poignée : non comprise, trou poignée et tire-doigt usinée<BR/>- Recoupable : non<BR/>- La pose sur cloison humide (exemples : carreaux de plâtre, briques + plâtre) doit se faire en priorité sur huisserie fin de chantier avec utilisation d\u2019un précadre. S'il n\u2019y a pas d\u2019huisserie fin de chantier, alors appliquer un bouche pore sur le bout du poteau pour éviter les remontées d\u2019humidité, et sur la feuillure en contact avec la cloison humide."
            },
            "additionalDesc2": {"locale": "fr"},
            "imageThumbnail": {"locale": "fr"}
        },
        {
            "attributeValueList": {"attributeValue": [
                {
                    "attrIdentifier": "ATC-AUSSI-SUR-MESURE",
                    "attrUsage": 2,
                    "valueDecimal": {
                        "locale": "fr",
                        "content": 0
                    },
                    "attrSequence": 0
                },
                {
                    "valueIdentifier": "K61",
                    "attrIdentifier": "ATC-CHANT",
                    "valueString": {
                        "locale": "fr",
                        "content": "Rive droite"
                    },
                    "attrUsage": 2,
                    "attrSequence": 0
                },
                {
                    "attrIdentifier": "ATC-COULEUR-CARTE",
                    "attrUsage": 2,
                    "valueDecimal": {
                        "locale": "fr",
                        "content": 0
                    },
                    "attrSequence": 0
                },
                {
                    "attrIdentifier": "ATC-FAB-EN-FRANCE",
                    "attrUsage": 2,
                    "valueDecimal": {
                        "locale": "fr",
                        "content": 0
                    },
                    "attrSequence": 0
                },
                {
                    "attrIdentifier": "ATC-FAB-PAR-LAPEYRE",
                    "attrUsage": 2,
                    "valueDecimal": {
                        "locale": "fr",
                        "content": 0
                    },
                    "attrSequence": 0
                },
                {
                    "valueIdentifier": "V47",
                    "attrIdentifier": "ATC-GAMME-SPECIFIQUE",
                    "valueString": {
                        "locale": "fr",
                        "content": "Portes intérieures"
                    },
                    "attrUsage": 2,
                    "attrSequence": 0
                },
                {
                    "attrIdentifier": "ATC-HAUTEUR-TOTALE",
                    "attrUsage": 2,
                    "valueDecimal": {
                        "locale": "fr",
                        "content": 204
                    },
                    "attrSequence": 0
                },
                {
                    "attrIdentifier": "ATC-LARGEUR-PASSAGE",
                    "attrUsage": 2,
                    "valueDecimal": {
                        "locale": "fr",
                        "content": 91.4
                    },
                    "attrSequence": 0
                },
                {
                    "attrIdentifier": "ATC-LARGEUR-TOTALE",
                    "attrUsage": 2,
                    "valueDecimal": {
                        "locale": "fr",
                        "content": 93
                    },
                    "attrSequence": 0
                },
                {
                    "attrIdentifier": "ATC-NORME-FSC",
                    "attrUsage": 2,
                    "valueDecimal": {
                        "locale": "fr",
                        "content": 0
                    },
                    "attrSequence": 0
                },
                {
                    "attrIdentifier": "ATC-NORME-PEFC",
                    "attrUsage": 2,
                    "valueDecimal": {
                        "locale": "fr",
                        "content": 0
                    },
                    "attrSequence": 0
                },
                {
                    "valueIdentifier": "K31",
                    "attrIdentifier": "ATC-PRODUIT",
                    "valueString": {
                        "locale": "fr",
                        "content": "Porte coulissante"
                    },
                    "attrUsage": 2,
                    "attrSequence": 0
                },
                {
                    "attrIdentifier": "ATD-CategorieCDG",
                    "valueString": {
                        "locale": "fr",
                        "content": "G3876-PORTES CHENE PLAQUE"
                    },
                    "attrUsage": 2,
                    "attrSequence": 0
                },
                {
                    "attrIdentifier": "ATD-FamilleCDG",
                    "valueString": {
                        "locale": "fr",
                        "content": "G17-PORTES INTERIEURES"
                    },
                    "attrUsage": 2,
                    "attrSequence": 0
                },
                {
                    "attrIdentifier": "ATD-LibelleCommercial",
                    "valueString": {
                        "locale": "fr",
                        "content": "Porte coulissante QUADRAL 4 panneaux plaqué chêne H.204 x l.93 cm"
                    },
                    "attrUsage": 2,
                    "attrSequence": 0
                },
                {
                    "attrIdentifier": "ATD-SousCategorieCDG",
                    "valueString": {
                        "locale": "fr",
                        "content": "G13166-QUADRAL PLEIN"
                    },
                    "attrUsage": 2,
                    "attrSequence": 0
                },
                {
                    "attrIdentifier": "ATD-SousCategorieCDG2",
                    "valueString": {
                        "locale": "fr",
                        "content": "2550930-PS COUL QUADRAL 4 PANNEAUX 204X93"
                    },
                    "attrUsage": 2,
                    "attrSequence": 0
                },
                {
                    "attrIdentifier": "ATD-SousCategorieCDG3",
                    "valueString": {
                        "locale": "fr",
                        "content": "N/A"
                    },
                    "attrUsage": 2,
                    "attrSequence": 0
                },
                {
                    "attrIdentifier": "ATD-SousFamilleCDG",
                    "valueString": {
                        "locale": "fr",
                        "content": "G729-PORTES COULISSANTES"
                    },
                    "attrUsage": 2,
                    "attrSequence": 0
                },
                {
                    "attrIdentifier": "ATD-UniverCDG",
                    "valueString": {
                        "locale": "fr",
                        "content": "G2-INTERIEUR"
                    },
                    "attrUsage": 2,
                    "attrSequence": 0
                },
                {
                    "attrIdentifier": "ATDDiffusionWebLive",
                    "attrUsage": 2,
                    "valueDecimal": {
                        "locale": "fr",
                        "content": 1
                    },
                    "attrSequence": 0
                },
                {
                    "attrIdentifier": "ATDDiffusionWebWork",
                    "attrUsage": 2,
                    "valueDecimal": {
                        "locale": "fr",
                        "content": 1
                    },
                    "attrSequence": 0
                },
                {
                    "attrIdentifier": "ATDProductPath",
                    "valueString": {
                        "locale": "fr",
                        "content": "G2/G17/G729/G3876/G13166/"
                    },
                    "attrUsage": 2,
                    "attrSequence": 0
                },
                {
                    "attrIdentifier": "ATS-CodeADA",
                    "attrUsage": 2,
                    "valueDecimal": {
                        "locale": "fr",
                        "content": 2550930
                    },
                    "attrSequence": 0
                },
                {
                    "valueIdentifier": "FRA-fr",
                    "attrIdentifier": "ATS-CurrentContextID",
                    "valueString": {
                        "locale": "fr",
                        "content": "RESEAU_FRANCE"
                    },
                    "attrUsage": 2,
                    "attrSequence": 0
                },
                {
                    "valueIdentifier": "CCU0004-ATC-COULEUR-DG2",
                    "attrIdentifier": "CCU0004-ATC-COULEUR",
                    "valueString": {
                        "locale": "fr",
                        "content": "Chêne plaqué brut"
                    },
                    "attrUsage": 2,
                    "attrSequence": 0
                },
                {
                    "valueIdentifier": "CCU0004-ATC-EPAISSEUR-PORTE-40",
                    "attrIdentifier": "CCU0004-ATC-EPAISSEUR-PORTE",
                    "attrUsage": 2,
                    "valueDecimal": {
                        "locale": "fr",
                        "content": 40
                    },
                    "attrSequence": 0
                },
                {
                    "valueIdentifier": "CCU0004-ATC-FINITION-G04",
                    "attrIdentifier": "CCU0004-ATC-FINITION",
                    "valueString": {
                        "locale": "fr",
                        "content": "Décor structuré"
                    },
                    "attrUsage": 2,
                    "attrSequence": 0
                },
                {
                    "valueIdentifier": "CCU0004-ATC-MATERIAU-222",
                    "attrIdentifier": "CCU0004-ATC-MATERIAU",
                    "valueString": {
                        "locale": "fr",
                        "content": "Mdf"
                    },
                    "attrUsage": 2,
                    "attrSequence": 0
                },
                {
                    "valueIdentifier": "CCU0004-ATC-NB-VANTAUX-1",
                    "attrIdentifier": "CCU0004-ATC-NB-VANTAUX",
                    "attrUsage": 2,
                    "valueDecimal": {
                        "locale": "fr",
                        "content": 1
                    },
                    "attrSequence": 0
                },
                {
                    "valueIdentifier": "CCU0004-COMMUNES-3-COMM-ASPECT-CL4",
                    "attrIdentifier": "CCU0004-COMMUNES-3-COMM-ASPECT",
                    "valueString": {
                        "locale": "fr",
                        "content": "Structuré"
                    },
                    "attrUsage": 2,
                    "attrSequence": 0
                },
                {
                    "valueIdentifier": "CCU0004-COMMUNES-3-COMM-TYPE-MATERIAU-015",
                    "attrIdentifier": "CCU0004-COMMUNES-3-COMM-TYPE-MATERIAU",
                    "valueString": {
                        "locale": "fr",
                        "content": "Bois"
                    },
                    "attrUsage": 2,
                    "attrSequence": 0
                },
                {
                    "valueIdentifier": "CCU0004-DIMENSIONS-COMMUNES-DIM-HAUTEUR-204",
                    "attrIdentifier": "CCU0004-DIMENSIONS-COMMUNES-DIM-HAUTEUR",
                    "attrUsage": 2,
                    "valueDecimal": {
                        "locale": "fr",
                        "content": 204
                    },
                    "attrSequence": 0
                },
                {
                    "valueIdentifier": "CCU0004-DIMENSIONS-COMMUNES-DIM-LARGEUR-93",
                    "attrIdentifier": "CCU0004-DIMENSIONS-COMMUNES-DIM-LARGEUR",
                    "attrUsage": 1,
                    "valueDecimal": {
                        "locale": "fr",
                        "content": 93
                    },
                    "attrSequence": 0
                },
                {
                    "valueIdentifier": "CCU0004-DIMENSIONS-COMMUNES-DIM-POIDS-23",
                    "attrIdentifier": "CCU0004-DIMENSIONS-COMMUNES-DIM-POIDS",
                    "attrUsage": 2,
                    "valueDecimal": {
                        "locale": "fr",
                        "content": 23
                    },
                    "attrSequence": 0
                },
                {
                    "valueIdentifier": "CCU0004-DIMENSIONS-COMMUNES-DIM-PROFONDEUR-9",
                    "attrIdentifier": "CCU0004-DIMENSIONS-COMMUNES-DIM-PROFONDEUR",
                    "attrUsage": 2,
                    "valueDecimal": {
                        "locale": "fr",
                        "content": 9
                    },
                    "attrSequence": 0
                },
                {
                    "attrIdentifier": "COMMUNE-COMM-ART-ETQ-LS",
                    "attrUsage": 2,
                    "valueDecimal": {
                        "locale": "fr",
                        "content": 0
                    },
                    "attrSequence": 0
                },
                {
                    "valueIdentifier": "ART",
                    "attrIdentifier": "COMMUNE-COMM-ART-TYP-TARIF",
                    "valueString": {
                        "locale": "fr",
                        "content": "PRIX DEFINI"
                    },
                    "attrUsage": 2,
                    "attrSequence": 0
                },
                {
                    "valueIdentifier": "ORD",
                    "attrIdentifier": "COMMUNE-COMM-ART-TYPE",
                    "valueString": {
                        "locale": "fr",
                        "content": "ORDINAIRE"
                    },
                    "attrUsage": 2,
                    "attrSequence": 0
                },
                {
                    "valueIdentifier": "SO",
                    "attrIdentifier": "COMMUNE-SUITE-COMM-ART-DUREE-VIE",
                    "valueString": {
                        "locale": "fr",
                        "content": "SANS OBJET"
                    },
                    "attrUsage": 2,
                    "attrSequence": 0
                },
                {
                    "attrIdentifier": "COMMUNE-SUITE-COMM-ART-INFLAMMABLE",
                    "attrUsage": 2,
                    "valueDecimal": {
                        "locale": "fr",
                        "content": 0
                    },
                    "attrSequence": 0
                },
                {
                    "valueIdentifier": "CDG",
                    "attrIdentifier": "COMMUNE-SUITE-SPEC-NAT-NIVEAU",
                    "valueString": {
                        "locale": "fr",
                        "content": "Coeur De Gamme"
                    },
                    "attrUsage": 2,
                    "attrSequence": 0
                },
                {
                    "valueIdentifier": "CTP",
                    "attrIdentifier": "COMMUNE-SUITE-SPEC-NAT-STYLE",
                    "valueString": {
                        "locale": "fr",
                        "content": "Contemporain"
                    },
                    "attrUsage": 2,
                    "attrSequence": 0
                },
                {
                    "attrIdentifier": "COMMUNES-3-ACHAT-LOCAL",
                    "attrUsage": 2,
                    "valueDecimal": {
                        "locale": "fr",
                        "content": 0
                    },
                    "attrSequence": 0
                },
                {
                    "attrIdentifier": "COMMUNES-3-COMM-ADAP-DIM",
                    "attrUsage": 2,
                    "valueDecimal": {
                        "locale": "fr",
                        "content": 0
                    },
                    "attrSequence": 0
                },
                {
                    "attrIdentifier": "COMMUNES-3-COMM-ART-EXCLUS-VERI",
                    "attrUsage": 2,
                    "valueDecimal": {
                        "locale": "fr",
                        "content": 0
                    },
                    "attrSequence": 0
                },
                {
                    "attrIdentifier": "COMMUNES-3-COMM-COEF-VOL",
                    "attrUsage": 2,
                    "valueDecimal": {
                        "locale": "fr",
                        "content": 1
                    },
                    "attrSequence": 0
                },
                {
                    "attrIdentifier": "COMMUNES-3-COMM-DIFFUSION-WEB",
                    "attrUsage": 2,
                    "valueDecimal": {
                        "locale": "fr",
                        "content": 1
                    },
                    "attrSequence": 0
                },
                {
                    "attrIdentifier": "COMMUNES-3-COMM-GARANTIE",
                    "valueString": {
                        "locale": "fr",
                        "content": "2 ans"
                    },
                    "attrUsage": 2,
                    "attrSequence": 0
                },
                {
                    "attrIdentifier": "COMMUNES-3-COMM-RENO-PLUS",
                    "attrUsage": 2,
                    "valueDecimal": {
                        "locale": "fr",
                        "content": 0
                    },
                    "attrSequence": 0
                },
                {
                    "valueIdentifier": "004",
                    "attrIdentifier": "COMMUNES-3-COMM-STD-SM-STDOPT",
                    "valueString": {
                        "locale": "fr",
                        "content": "Standard"
                    },
                    "attrUsage": 2,
                    "attrSequence": 0
                },
                {
                    "valueIdentifier": "001",
                    "attrIdentifier": "COMMUNES-3-COMM-TYPE-PDT",
                    "valueString": {
                        "locale": "fr",
                        "content": "Principal"
                    },
                    "attrUsage": 2,
                    "attrSequence": 0
                },
                {
                    "attrIdentifier": "DIMENSIONS-COMMUNES-DIM-HAUTEUR-EMB",
                    "attrUsage": 2,
                    "valueDecimal": {
                        "locale": "fr",
                        "content": 205
                    },
                    "attrSequence": 0
                },
                {
                    "attrIdentifier": "DIMENSIONS-COMMUNES-DIM-LARGEUR-EMB",
                    "attrUsage": 2,
                    "valueDecimal": {
                        "locale": "fr",
                        "content": 94
                    },
                    "attrSequence": 0
                },
                {
                    "attrIdentifier": "DIMENSIONS-COMMUNES-DIM-PROFONDEUR-EMB",
                    "attrUsage": 2,
                    "valueDecimal": {
                        "locale": "fr",
                        "content": 5
                    },
                    "attrSequence": 0
                },
                {
                    "attrIdentifier": "DIMENSIONS-COMMUNES-DIM-VOLUME",
                    "attrUsage": 2,
                    "valueDecimal": {
                        "locale": "fr",
                        "content": 170.748
                    },
                    "attrSequence": 0
                },
                {
                    "attrIdentifier": "IS-ELIGIBLE-PROMO-SIMPLE",
                    "valueString": {
                        "locale": "fr",
                        "content": "NON"
                    },
                    "attrUsage": 2,
                    "attrSequence": 0
                },
                {
                    "attrIdentifier": "RESEAU-DISTRIBUTION-RESEAU-ANTILLES",
                    "attrUsage": 2,
                    "valueDecimal": {
                        "locale": "fr",
                        "content": 1
                    },
                    "attrSequence": 0
                },
                {
                    "attrIdentifier": "RESEAU-DISTRIBUTION-RESEAU-PLATEFORME",
                    "attrUsage": 2,
                    "valueDecimal": {
                        "locale": "fr",
                        "content": 0
                    },
                    "attrSequence": 0
                },
                {
                    "attrIdentifier": "RESEAU-DISTRIBUTION-RESEAU-REUNION",
                    "attrUsage": 2,
                    "valueDecimal": {
                        "locale": "fr",
                        "content": 1
                    },
                    "attrSequence": 0
                },
                {
                    "attrIdentifier": "RESEAU-DISTRIBUTION-RESEAU-SUISSE",
                    "attrUsage": 2,
                    "valueDecimal": {
                        "locale": "fr",
                        "content": 1
                    },
                    "attrSequence": 0
                },
                {
                    "valueIdentifier": 164,
                    "attrIdentifier": "SPEC-FAM-CHX",
                    "valueString": {
                        "locale": "fr",
                        "content": "PLEIN"
                    },
                    "attrUsage": 2,
                    "attrSequence": 0
                },
                {
                    "valueIdentifier": 687,
                    "attrIdentifier": "SPEC-FAM-CMA",
                    "valueString": {
                        "locale": "fr",
                        "content": "RIVE DROITE"
                    },
                    "attrUsage": 2,
                    "attrSequence": 0
                },
                {
                    "valueIdentifier": 230,
                    "attrIdentifier": "SPEC-FAM-DET",
                    "valueString": {
                        "locale": "fr",
                        "content": "UN VANTAIL"
                    },
                    "attrUsage": 2,
                    "attrSequence": 0
                },
                {
                    "valueIdentifier": 379,
                    "attrIdentifier": "SPEC-FAM-GAM",
                    "valueString": {
                        "locale": "fr",
                        "content": "MENUISEE"
                    },
                    "attrUsage": 2,
                    "attrSequence": 0
                },
                {
                    "valueIdentifier": 115,
                    "attrIdentifier": "SPEC-FAM-MDE",
                    "valueString": {
                        "locale": "fr",
                        "content": "STANDARD"
                    },
                    "attrUsage": 2,
                    "attrSequence": 0
                },
                {
                    "valueIdentifier": "R95",
                    "attrIdentifier": "SPEC-FAM-NMA",
                    "valueString": {
                        "locale": "fr",
                        "content": "CHENE PLAQUE"
                    },
                    "attrUsage": 2,
                    "attrSequence": 0
                },
                {
                    "valueIdentifier": 1,
                    "attrIdentifier": "SPECIF-RESO-XXX-SPEC-RESO-CATAL-TYPE",
                    "valueString": {
                        "locale": "fr",
                        "content": "MENUISERIES"
                    },
                    "attrUsage": 2,
                    "attrSequence": 0
                },
                {
                    "attrIdentifier": "SPECIF-RESO-XXX-SPEC-RESO-DEG",
                    "attrUsage": 2,
                    "valueDecimal": {
                        "locale": "fr",
                        "content": 0
                    },
                    "attrSequence": 0
                },
                {
                    "attrIdentifier": "SPECIF-RESO-XXX-SPEC-RESO-ENV-DEPOT",
                    "attrUsage": 2,
                    "valueDecimal": {
                        "locale": "fr",
                        "content": 1
                    },
                    "attrSequence": 0
                },
                {
                    "valueIdentifier": 0,
                    "attrIdentifier": "SPECIF-RESO-XXX-SPEC-RESO-OBSO",
                    "valueString": {
                        "locale": "fr",
                        "content": "A l'offre"
                    },
                    "attrUsage": 2,
                    "attrSequence": 0
                },
                {
                    "attrIdentifier": "SPECIF-RESO-XXX-SPEC-RESO-REMISE",
                    "attrUsage": 2,
                    "valueDecimal": {
                        "locale": "fr",
                        "content": 1
                    },
                    "attrSequence": 0
                },
                {
                    "valueIdentifier": 1,
                    "attrIdentifier": "SPECIF-RESO-XXX-SPEC-RESO-TVA",
                    "valueString": {
                        "locale": "fr",
                        "content": "20 %"
                    },
                    "attrUsage": 2,
                    "attrSequence": 0
                },
                {
                    "valueIdentifier": 3,
                    "attrIdentifier": "SPECIF-RESO-XXX-SPEC-RESO-TVA2",
                    "valueString": {
                        "locale": "fr",
                        "content": "10% (Pose)"
                    },
                    "attrUsage": 2,
                    "attrSequence": 0
                },
                {
                    "attrIdentifier": "categorieGoogle",
                    "valueString": {
                        "locale": "fr",
                        "content": 119
                    },
                    "attrUsage": 2,
                    "attrSequence": 0
                },
                {
                    "attrIdentifier": "colissimo",
                    "attrUsage": 2,
                    "valueDecimal": {
                        "locale": "fr",
                        "content": 0
                    },
                    "attrSequence": 0
                },
                {
                    "valueIdentifier": 0,
                    "attrIdentifier": "contrainteColisage",
                    "valueString": {
                        "locale": "fr",
                        "content": 0
                    },
                    "attrUsage": 2,
                    "attrSequence": 0
                },
                {
                    "attrIdentifier": "isLivraisonDirecte",
                    "attrUsage": 2,
                    "valueDecimal": {
                        "locale": "fr",
                        "content": 0
                    },
                    "attrSequence": 0
                },
                {
                    "attrIdentifier": "poids",
                    "attrUsage": 2,
                    "valueDecimal": {
                        "locale": "fr",
                        "content": 23.31
                    },
                    "attrSequence": 0
                },
                {
                    "attrIdentifier": "priceLabel",
                    "valueString": {
                        "locale": "fr",
                        "content": "Prix pour la dimension H 204 x L 93 cm"
                    },
                    "attrUsage": 2,
                    "attrSequence": 0
                },
                {
                    "valueIdentifier": "UN",
                    "attrIdentifier": "uniteSecondaire",
                    "valueString": {
                        "locale": "fr",
                        "content": "UN"
                    },
                    "attrUsage": 2,
                    "attrSequence": 0
                },
                {
                    "valueIdentifier": "UN",
                    "attrIdentifier": "uniteVente",
                    "valueString": {
                        "locale": "fr",
                        "content": "UN"
                    },
                    "attrUsage": 2,
                    "attrSequence": 0
                },
                {
                    "valueIdentifier": "UN",
                    "attrIdentifier": "uniteVenteLegale",
                    "valueString": {
                        "locale": "fr",
                        "content": "UN"
                    },
                    "attrUsage": 2,
                    "attrSequence": 0
                }
            ]},
            "isDefault": false,
            "seoItem": {"urlKeyword": {
                "locale": "fr",
                "content": "porte-coulissante-quadral-4-panneaux-plaque-chene-h-204-x-l-93-cm-2550930"
            }},
            "imageFull": {"locale": "fr"},
            "shortDesc": {"locale": "fr"},
            "published": {
                "locale": "fr",
                "content": false
            },
            "label": {
                "locale": "fr",
                "content": "Porte coulissante QUADRAL 4 panneaux plaqué chêne H.204 x l.93 cm"
            },
            "sku": 2550930,
            "additionalDesc1": {"locale": "fr"},
            "longDesc": {
                "locale": "fr",
                "content": "- Produit : Porte coulissante <BR/>- Modèle : Quadral 4 panneaux<BR/>- Type de porte : chêne plaqué<BR/>- Type de chant : rive droite<BR/>- Composition : Panneaux en aggloméré revêtu d'un placage chêne  1er choix à vernir<BR/>- Montants et traverses en MDF ou aggloméré plaqué chêne<BR/>- Finition : incolore sur demande en magasin<BR/>- Hauteur de porte : 204 cm<BR/>- Largeur de porte : 73, 83, 93 cm<BR/>- Epaisseur de porte : 40mm<BR/>- Serrure magnétique à clé<BR/>- Poignée : non comprise, trou poignée et tire-doigt usinée<BR/>- Recoupable : non<BR/>- La pose sur cloison humide (exemples : carreaux de plâtre, briques + plâtre) doit se faire en priorité sur huisserie fin de chantier avec utilisation d\u2019un précadre. S'il n\u2019y a pas d\u2019huisserie fin de chantier, alors appliquer un bouche pore sur le bout du poteau pour éviter les remontées d\u2019humidité, et sur la feuillure en contact avec la cloison humide."
            },
            "additionalDesc2": {"locale": "fr"},
            "imageThumbnail": {"locale": "fr"}
        }
    ]},
    "keyword": {
        "locale": "fr",
        "content": "porte, coulissante, intérieur"
    },
    "seo": {
        "imageAltText": {
            "locale": "fr",
            "content": "Porte coulissante chêne plaqué Quadral pleine - Portes - Lapeyre"
        },
        "pageTitle": {
            "locale": "fr",
            "content": "Porte coulissante chêne plaqué Quadral pleine - Portes - Lapeyre"
        },
        "metaDesc": {
            "locale": "fr",
            "content": "Porte bois à rive droite en Chêne plaqué à l'esthétique contemporaine. Fabriqué dans nos usines françaises. Existe également en version 4 panneaux vitrés sur ce site."
        },
        "urlKeyword": {
            "locale": "fr",
            "content": "porte-coulissante-chene-plaque-quadral-pleine-FPC1582294"
        },
        "metaKeyword": {
            "locale": "fr",
            "content": "porte, coulissante, intérieur"
        }
    },
    "partnumber": "FPC1582294",
    "longDesc": {
        "locale": "fr",
        "content": "- Produit : Porte coulissante <BR/>- Modèle : Quadral 4 panneaux<BR/>- Type de porte : chêne plaqué<BR/>- Type de chant : rive droite<BR/>- Composition : Panneaux en aggloméré revêtu d'un placage chêne  1er choix à vernir<BR/>- Montants et traverses en MDF ou aggloméré plaqué chêne<BR/>- Finition : incolore sur demande en magasin<BR/>- Hauteur de porte : 204 cm<BR/>- Largeur de porte : 73, 83, 93 cm<BR/>- Epaisseur de porte : 40mm<BR/>- Serrure magnétique à clé<BR/>- Poignée : non comprise, trou poignée et tire-doigt usinée<BR/>- Recoupable : non<BR/>- La pose sur cloison humide (exemples : carreaux de plâtre, briques + plâtre) doit se faire en priorité sur huisserie fin de chantier avec utilisation d\u2019un précadre. S'il n\u2019y a pas d\u2019huisserie fin de chantier, alors appliquer un bouche pore sur le bout du poteau pour éviter les remontées d\u2019humidité, et sur la feuillure en contact avec la cloison humide."
    },
    "imageThumbnail": {"locale": "fr"}
}}