{"product": {
    "brandName": "Lapeyre",
    "brandPartnumber": 503,
    "categoriesParentList": {"categoryParent": {"categoryIdentifier": "porte-fenetre-chene-CCN688829"}},
    "imageFull": {
        "locale": "fr",
        "content": "/collMain/206/643/201206643.jpg"
    },
    "published": {
        "locale": "fr",
        "content": true
    },
    "label": {
        "locale": "fr",
        "content": "Porte-fenêtre Excellence Chêne"
    },
    "type": "SUR_MESURE",
    "additionalDesc1": {
        "locale": "fr",
        "content": "Porte-fenêtre Excellence bois sur-mesure disponible en 156 coloris mono ou bicouleur, personnalisable en formes, qualité de vitrages, accessoires et décorations. Fabriquées dans nos usines françaises, ces portes-fenêtres bénéficient sous condition d'un délais de 14 jours maximum."
    },
    "additionalDesc2": {"locale": "fr"},
    "attributeValueList": {"attributeValue": [
        {
            "attrIdentifier": "categorieGoogle",
            "valueString": {
                "locale": "fr",
                "content": 124
            },
            "attrUsage": 2,
            "attrSequence": 0
        },
        {
            "attrIdentifier": "colissimo",
            "attrUsage": 2,
            "valueDecimal": {
                "locale": "fr",
                "content": 0
            },
            "attrSequence": 0
        },
        {
            "valueIdentifier": 0,
            "attrIdentifier": "contrainteColisage",
            "valueString": {
                "locale": "fr",
                "content": 0
            },
            "attrUsage": 2,
            "attrSequence": 0
        },
        {
            "attrIdentifier": "priceLabel",
            "valueString": {
                "locale": "fr",
                "content": "Prix pour la dimension H  x L"
            },
            "attrUsage": 2,
            "attrSequence": 0
        },
        {
            "valueIdentifier": "UN",
            "attrIdentifier": "uniteSecondaire",
            "valueString": {
                "locale": "fr",
                "content": "UN"
            },
            "attrUsage": 2,
            "attrSequence": 0
        },
        {
            "valueIdentifier": "UN",
            "attrIdentifier": "uniteVente",
            "valueString": {
                "locale": "fr",
                "content": "UN"
            },
            "attrUsage": 2,
            "attrSequence": 0
        },
        {
            "valueIdentifier": "UN",
            "attrIdentifier": "uniteVenteLegale",
            "valueString": {
                "locale": "fr",
                "content": "UN"
            },
            "attrUsage": 2,
            "attrSequence": 0
        }
    ]},
    "action": "add",
    "shortDesc": {"locale": "fr"},
    "itemList": {"item": {
        "attributeValueList": {"attributeValue": [
            {
                "attrIdentifier": "ATC-AUSSI-SUR-MESURE",
                "attrUsage": 2,
                "valueDecimal": {
                    "locale": "fr",
                    "content": 1
                },
                "attrSequence": 0
            },
            {
                "attrIdentifier": "ATC-COULEUR-CARTE",
                "attrUsage": 2,
                "valueDecimal": {
                    "locale": "fr",
                    "content": 1
                },
                "attrSequence": 0
            },
            {
                "attrIdentifier": "ATC-FAB-EN-FRANCE",
                "attrUsage": 2,
                "valueDecimal": {
                    "locale": "fr",
                    "content": 1
                },
                "attrSequence": 0
            },
            {
                "attrIdentifier": "ATC-FAB-PAR-LAPEYRE",
                "attrUsage": 2,
                "valueDecimal": {
                    "locale": "fr",
                    "content": 1
                },
                "attrSequence": 0
            },
            {
                "valueIdentifier": "D",
                "attrIdentifier": "ATC-FORME",
                "valueString": {
                    "locale": "fr",
                    "content": "Droite"
                },
                "attrUsage": 2,
                "attrSequence": 0
            },
            {
                "valueIdentifier": "N96",
                "attrIdentifier": "ATC-MENUISERIE",
                "valueString": {
                    "locale": "fr",
                    "content": "Frappe"
                },
                "attrUsage": 2,
                "attrSequence": 0
            },
            {
                "attrIdentifier": "ATC-NORME-FSC",
                "attrUsage": 2,
                "valueDecimal": {
                    "locale": "fr",
                    "content": 0
                },
                "attrSequence": 0
            },
            {
                "attrIdentifier": "ATC-NORME-NF",
                "attrUsage": 2,
                "valueDecimal": {
                    "locale": "fr",
                    "content": 1
                },
                "attrSequence": 0
            },
            {
                "attrIdentifier": "ATD-CategorieCDG",
                "valueString": {
                    "locale": "fr",
                    "content": "G12951-EXCELLENCE CHENE"
                },
                "attrUsage": 2,
                "attrSequence": 0
            },
            {
                "attrIdentifier": "ATD-FamilleCDG",
                "valueString": {
                    "locale": "fr",
                    "content": "G120-FENETRES BOIS"
                },
                "attrUsage": 2,
                "attrSequence": 0
            },
            {
                "attrIdentifier": "ATD-LibelleCommercial",
                "valueString": {
                    "locale": "fr",
                    "content": "Menuiserie ouverture battante EXCELLENCE Chêne Rectangulaire - Sur mesure - DEG"
                },
                "attrUsage": 2,
                "attrSequence": 0
            },
            {
                "attrIdentifier": "ATD-SousCategorieCDG",
                "valueString": {
                    "locale": "fr",
                    "content": "G56881-FORME DROITE SUR MESURE"
                },
                "attrUsage": 2,
                "attrSequence": 0
            },
            {
                "attrIdentifier": "ATD-SousCategorieCDG2",
                "valueString": {
                    "locale": "fr",
                    "content": "G45125-FRAPPE"
                },
                "attrUsage": 2,
                "attrSequence": 0
            },
            {
                "attrIdentifier": "ATD-SousCategorieCDG3",
                "valueString": {
                    "locale": "fr",
                    "content": "2347700-MEN. FRAP. RECTANG. EXCEL. CHENE S/M"
                },
                "attrUsage": 2,
                "attrSequence": 0
            },
            {
                "attrIdentifier": "ATD-SousFamilleCDG",
                "valueString": {
                    "locale": "fr",
                    "content": "G3792-FRAPPE BOIS"
                },
                "attrUsage": 2,
                "attrSequence": 0
            },
            {
                "attrIdentifier": "ATD-UniverCDG",
                "valueString": {
                    "locale": "fr",
                    "content": "G13-FENETRES"
                },
                "attrUsage": 2,
                "attrSequence": 0
            },
            {
                "attrIdentifier": "ATD-Vue360",
                "valueString": {
                    "locale": "fr",
                    "content": "http://www.lapeyre.fr/menuiserie-ouverture-battante-excellence-chene-rectangulaire-sur-mesure-deg-2347700"
                },
                "attrUsage": 2,
                "attrSequence": 0
            },
            {
                "attrIdentifier": "ATD-Vue360Asset",
                "valueString": {
                    "locale": "fr",
                    "content": "http://www.lapeyre.fr/img/catalogue/collMain/amb/@01/2347700@AMB@01.jpg"
                },
                "attrUsage": 2,
                "attrSequence": 0
            },
            {
                "attrIdentifier": "ATDDiffusionWebLive",
                "attrUsage": 2,
                "valueDecimal": {
                    "locale": "fr",
                    "content": 1
                },
                "attrSequence": 0
            },
            {
                "attrIdentifier": "ATDDiffusionWebWork",
                "attrUsage": 2,
                "valueDecimal": {
                    "locale": "fr",
                    "content": 1
                },
                "attrSequence": 0
            },
            {
                "attrIdentifier": "ATDProductPath",
                "valueString": {
                    "locale": "fr",
                    "content": "G13/G120/G3792/G12951/G56881/G45125/"
                },
                "attrUsage": 2,
                "attrSequence": 0
            },
            {
                "valueIdentifier": "FRA-fr",
                "attrIdentifier": "ATS-CurrentContextID",
                "valueString": {
                    "locale": "fr",
                    "content": "RESEAU_FRANCE"
                },
                "attrUsage": 2,
                "attrSequence": 0
            },
            {
                "attrIdentifier": "COMMUNE-COMM-ART-ETQ-LS",
                "attrUsage": 2,
                "valueDecimal": {
                    "locale": "fr",
                    "content": 0
                },
                "attrSequence": 0
            },
            {
                "valueIdentifier": "MES",
                "attrIdentifier": "COMMUNE-COMM-ART-TYP-TARIF",
                "valueString": {
                    "locale": "fr",
                    "content": "PRIX SUR MESURE"
                },
                "attrUsage": 2,
                "attrSequence": 0
            },
            {
                "valueIdentifier": "STA",
                "attrIdentifier": "COMMUNE-COMM-ART-TYPE",
                "valueString": {
                    "locale": "fr",
                    "content": "GENERIQUE"
                },
                "attrUsage": 2,
                "attrSequence": 0
            },
            {
                "valueIdentifier": "SO",
                "attrIdentifier": "COMMUNE-SUITE-COMM-ART-DUREE-VIE",
                "valueString": {
                    "locale": "fr",
                    "content": "SANS OBJET"
                },
                "attrUsage": 2,
                "attrSequence": 0
            },
            {
                "attrIdentifier": "COMMUNE-SUITE-COMM-ART-INFLAMMABLE",
                "attrUsage": 2,
                "valueDecimal": {
                    "locale": "fr",
                    "content": 0
                },
                "attrSequence": 0
            },
            {
                "valueIdentifier": "HDG",
                "attrIdentifier": "COMMUNE-SUITE-SPEC-NAT-NIVEAU",
                "valueString": {
                    "locale": "fr",
                    "content": "Haut De Gamme"
                },
                "attrUsage": 2,
                "attrSequence": 0
            },
            {
                "valueIdentifier": "AUT",
                "attrIdentifier": "COMMUNE-SUITE-SPEC-NAT-STYLE",
                "valueString": {
                    "locale": "fr",
                    "content": "Authentique"
                },
                "attrUsage": 2,
                "attrSequence": 0
            },
            {
                "attrIdentifier": "COMMUNES-3-ACHAT-LOCAL",
                "attrUsage": 2,
                "valueDecimal": {
                    "locale": "fr",
                    "content": 0
                },
                "attrSequence": 0
            },
            {
                "attrIdentifier": "COMMUNES-3-COMM-ADAP-DIM",
                "attrUsage": 2,
                "valueDecimal": {
                    "locale": "fr",
                    "content": 0
                },
                "attrSequence": 0
            },
            {
                "attrIdentifier": "COMMUNES-3-COMM-ART-EXCLUS-VERI",
                "attrUsage": 2,
                "valueDecimal": {
                    "locale": "fr",
                    "content": 0
                },
                "attrSequence": 0
            },
            {
                "attrIdentifier": "COMMUNES-3-COMM-COEF-VOL",
                "attrUsage": 2,
                "valueDecimal": {
                    "locale": "fr",
                    "content": 1
                },
                "attrSequence": 0
            },
            {
                "attrIdentifier": "COMMUNES-3-COMM-DIFFUSION-WEB",
                "attrUsage": 2,
                "valueDecimal": {
                    "locale": "fr",
                    "content": 1
                },
                "attrSequence": 0
            },
            {
                "attrIdentifier": "COMMUNES-3-COMM-GARANTIE",
                "valueString": {
                    "locale": "fr",
                    "content": "20 ans"
                },
                "attrUsage": 2,
                "attrSequence": 0
            },
            {
                "valueIdentifier": 503,
                "attrIdentifier": "COMMUNES-3-COMM-MARQUE-COM",
                "valueString": {
                    "locale": "fr",
                    "content": "Lapeyre"
                },
                "attrUsage": 2,
                "attrSequence": 0
            },
            {
                "attrIdentifier": "COMMUNES-3-COMM-RENO-PLUS",
                "attrUsage": 2,
                "valueDecimal": {
                    "locale": "fr",
                    "content": 0
                },
                "attrSequence": 0
            },
            {
                "valueIdentifier": "005",
                "attrIdentifier": "COMMUNES-3-COMM-STD-SM-STDOPT",
                "valueString": {
                    "locale": "fr",
                    "content": "Sur mesure"
                },
                "attrUsage": 2,
                "attrSequence": 0
            },
            {
                "valueIdentifier": "015",
                "attrIdentifier": "COMMUNES-3-COMM-TYPE-MATERIAU",
                "valueString": {
                    "locale": "fr",
                    "content": "Bois"
                },
                "attrUsage": 2,
                "attrSequence": 0
            },
            {
                "valueIdentifier": "001",
                "attrIdentifier": "COMMUNES-3-COMM-TYPE-PDT",
                "valueString": {
                    "locale": "fr",
                    "content": "Principal"
                },
                "attrUsage": 2,
                "attrSequence": 0
            },
            {
                "valueIdentifier": "G59",
                "attrIdentifier": "COMMUNES-3-COULEUR-MACRO",
                "valueString": {
                    "locale": "fr",
                    "content": "Autre"
                },
                "attrUsage": 2,
                "attrSequence": 0
            },
            {
                "attrIdentifier": "DIMENSIONS-COMMUNES-DIM-HAUTEUR-EMB",
                "attrUsage": 2,
                "valueDecimal": {
                    "locale": "fr",
                    "content": 0
                },
                "attrSequence": 0
            },
            {
                "attrIdentifier": "DIMENSIONS-COMMUNES-DIM-LARGEUR-EMB",
                "attrUsage": 2,
                "valueDecimal": {
                    "locale": "fr",
                    "content": 0
                },
                "attrSequence": 0
            },
            {
                "attrIdentifier": "DIMENSIONS-COMMUNES-DIM-PROFONDEUR-EMB",
                "attrUsage": 2,
                "valueDecimal": {
                    "locale": "fr",
                    "content": 0
                },
                "attrSequence": 0
            },
            {
                "attrIdentifier": "DIMENSIONS-COMMUNES-DIM-VOLUME",
                "attrUsage": 2,
                "valueDecimal": {
                    "locale": "fr",
                    "content": 0
                },
                "attrSequence": 0
            },
            {
                "attrIdentifier": "RESEAU-DISTRIBUTION-RESEAU-ANTILLES",
                "attrUsage": 2,
                "valueDecimal": {
                    "locale": "fr",
                    "content": 1
                },
                "attrSequence": 0
            },
            {
                "attrIdentifier": "RESEAU-DISTRIBUTION-RESEAU-PLATEFORME",
                "attrUsage": 2,
                "valueDecimal": {
                    "locale": "fr",
                    "content": 0
                },
                "attrSequence": 0
            },
            {
                "attrIdentifier": "RESEAU-DISTRIBUTION-RESEAU-REUNION",
                "attrUsage": 2,
                "valueDecimal": {
                    "locale": "fr",
                    "content": 1
                },
                "attrSequence": 0
            },
            {
                "attrIdentifier": "RESEAU-DISTRIBUTION-RESEAU-SUISSE",
                "attrUsage": 2,
                "valueDecimal": {
                    "locale": "fr",
                    "content": 1
                },
                "attrSequence": 0
            },
            {
                "valueIdentifier": 300,
                "attrIdentifier": "SPEC-FAM-CHX",
                "valueString": {
                    "locale": "fr",
                    "content": "DROIT / OUVERTURE FRANCAISE"
                },
                "attrUsage": 2,
                "attrSequence": 0
            },
            {
                "valueIdentifier": 155,
                "attrIdentifier": "SPEC-FAM-CMA",
                "valueString": {
                    "locale": "fr",
                    "content": "ISOLANTES"
                },
                "attrUsage": 2,
                "attrSequence": 0
            },
            {
                "valueIdentifier": "BOI",
                "attrIdentifier": "SPEC-FAM-GAM",
                "valueString": {
                    "locale": "fr",
                    "content": "BOIS"
                },
                "attrUsage": 2,
                "attrSequence": 0
            },
            {
                "valueIdentifier": 316,
                "attrIdentifier": "SPEC-FAM-MDE",
                "valueString": {
                    "locale": "fr",
                    "content": "SUR MESURE"
                },
                "attrUsage": 2,
                "attrSequence": 0
            },
            {
                "valueIdentifier": "CHE",
                "attrIdentifier": "SPEC-FAM-NMA",
                "valueString": {
                    "locale": "fr",
                    "content": "CHENE"
                },
                "attrUsage": 2,
                "attrSequence": 0
            },
            {
                "valueIdentifier": 1,
                "attrIdentifier": "SPECIF-RESO-XXX-SPEC-RESO-CATAL-TYPE",
                "valueString": {
                    "locale": "fr",
                    "content": "MENUISERIES"
                },
                "attrUsage": 2,
                "attrSequence": 0
            },
            {
                "attrIdentifier": "SPECIF-RESO-XXX-SPEC-RESO-DEG",
                "attrUsage": 2,
                "valueDecimal": {
                    "locale": "fr",
                    "content": 0
                },
                "attrSequence": 0
            },
            {
                "attrIdentifier": "SPECIF-RESO-XXX-SPEC-RESO-ENV-DEPOT",
                "attrUsage": 2,
                "valueDecimal": {
                    "locale": "fr",
                    "content": 1
                },
                "attrSequence": 0
            },
            {
                "valueIdentifier": 0,
                "attrIdentifier": "SPECIF-RESO-XXX-SPEC-RESO-OBSO",
                "valueString": {
                    "locale": "fr",
                    "content": "A l'offre"
                },
                "attrUsage": 2,
                "attrSequence": 0
            },
            {
                "attrIdentifier": "SPECIF-RESO-XXX-SPEC-RESO-REMISE",
                "attrUsage": 2,
                "valueDecimal": {
                    "locale": "fr",
                    "content": 1
                },
                "attrSequence": 0
            },
            {
                "valueIdentifier": 1,
                "attrIdentifier": "SPECIF-RESO-XXX-SPEC-RESO-TVA",
                "valueString": {
                    "locale": "fr",
                    "content": "20 %"
                },
                "attrUsage": 2,
                "attrSequence": 0
            },
            {
                "valueIdentifier": 4,
                "attrIdentifier": "SPECIF-RESO-XXX-SPEC-RESO-TVA2",
                "valueString": {
                    "locale": "fr",
                    "content": "5,5 % (Pose 2014)"
                },
                "attrUsage": 2,
                "attrSequence": 0
            },
            {
                "attrIdentifier": "categorieGoogle",
                "valueString": {
                    "locale": "fr",
                    "content": 124
                },
                "attrUsage": 2,
                "attrSequence": 0
            },
            {
                "attrIdentifier": "colissimo",
                "attrUsage": 2,
                "valueDecimal": {
                    "locale": "fr",
                    "content": 0
                },
                "attrSequence": 0
            },
            {
                "valueIdentifier": 0,
                "attrIdentifier": "contrainteColisage",
                "valueString": {
                    "locale": "fr",
                    "content": 0
                },
                "attrUsage": 2,
                "attrSequence": 0
            },
            {
                "attrIdentifier": "isLivraisonDirecte",
                "attrUsage": 2,
                "valueDecimal": {
                    "locale": "fr",
                    "content": 0
                },
                "attrSequence": 0
            },
            {
                "attrIdentifier": "poids",
                "attrUsage": 2,
                "valueDecimal": {
                    "locale": "fr",
                    "content": 0
                },
                "attrSequence": 0
            },
            {
                "attrIdentifier": "priceLabel",
                "valueString": {
                    "locale": "fr",
                    "content": "Prix pour la dimension H  x L"
                },
                "attrUsage": 2,
                "attrSequence": 0
            },
            {
                "valueIdentifier": "UN",
                "attrIdentifier": "uniteSecondaire",
                "valueString": {
                    "locale": "fr",
                    "content": "UN"
                },
                "attrUsage": 2,
                "attrSequence": 0
            },
            {
                "valueIdentifier": "UN",
                "attrIdentifier": "uniteVente",
                "valueString": {
                    "locale": "fr",
                    "content": "UN"
                },
                "attrUsage": 2,
                "attrSequence": 0
            },
            {
                "valueIdentifier": "UN",
                "attrIdentifier": "uniteVenteLegale",
                "valueString": {
                    "locale": "fr",
                    "content": "UN"
                },
                "attrUsage": 2,
                "attrSequence": 0
            }
        ]},
        "isDefault": true,
        "seoItem": {"urlKeyword": {
            "locale": "fr",
            "content": "menuiserie-ouverture-battante-excellence-chene-rectangulaire-sur-mesure-deg-2347700"
        }},
        "imageFull": {
            "locale": "fr",
            "content": "/collMain/206/643/201206643.jpg"
        },
        "shortDesc": {"locale": "fr"},
        "published": {
            "locale": "fr",
            "content": true
        },
        "label": {
            "locale": "fr",
            "content": "Menuiserie ouverture battante EXCELLENCE Chêne Rectangulaire - Sur mesure - DEG"
        },
        "sku": 2347700,
        "additionalDesc1": {"locale": "fr"},
        "longDesc": {
            "locale": "fr",
            "content": "- Type de menuiserie : Porte-fenêtre sur mesure<BR/>- Matériau: Chêne<BR/>- Couleur: Finition claire ou foncé<BR/>- Type d'ouverture: Battante<BR/>- Type de vantaux : de 1 à 4, avec ou sans soubassement, à clé<BR/>- Type de pose : en applique, en rénovation, en tunnel ou en feuillure<BR/>- Epaisseur de l'ouvrant 56 mm aboutage intérieur et extérieur.<BR/>- Epaisseur du dormant 45mm aboutage intérieur et extérieur<BR/>- Double vitrage : 24 mm Énergie STAR® traité faible émissivité avec gaz argon et intercalaire<BR/>- Haute Isolation Thermique Uw 1,5,  Ug = 1.0<BR/>- Isolation Acoustique: AC1 (RA ; tr = 28 dB)<BR/>- Etanchéité: A*4 E*7B V*A3.<BR/>- Double joint d\u2019isolation thermique et acoustique<BR/>- Grille de ventilation : auto-réglable ou hydro-réglable, disponible en option<BR/><BR/><B>- Options disponibles en magasins sur la gamme Excellence sur mesure :<\/B><BR/>* Couleurs préférentielles : 2 finitions lasurées (à base d'eau sans solvant)<BR/>* Autres couleurs : 156 au choix, disponibles en mono et bicoloration<BR/>* Vitrages : Double vitrage isolation acoustique, contrôle solaire, SGG bioclean®, sécurité des biens et des personnes<BR/>* Ouverture oscillo-battante<BR/>* Petits bois intégrés, collés ou en cadre amovible, crémones décoratives<BR/>* Volet roulant : intégré à la fenêtre et coffre demi-linteau (pour le neuf) ou Rénopro (pour la rénovation)<BR/>* Formes spéciales : cintrées, trapèze, triangulaire et ?il-de-b?uf<BR/><BR/><B>- Délai Express Garanti :<\/B><BR/>* Votre fenêtre sur mesure disponible en express dans votre magasin partout en France en 14 jours maximum,consultez nos conseillers-experts en magasins"
        },
        "additionalDesc2": {"locale": "fr"},
        "imageThumbnail": {
            "locale": "fr",
            "content": "/thumbnail/206/643/201206643.jpg"
        }
    }},
    "keyword": {
        "locale": "fr",
        "content": "menuiseries,ouverture,bois"
    },
    "seo": {
        "imageAltText": {
            "locale": "fr",
            "content": "Porte-fenêtre Excellence Chêne - Fenêtres - Lapeyre"
        },
        "pageTitle": {
            "locale": "fr",
            "content": "Porte-fenêtre Excellence Chêne - Fenêtres - Lapeyre"
        },
        "metaDesc": {
            "locale": "fr",
            "content": "Porte-fenêtre Excellence bois sur-mesure disponible en 156 coloris mono ou bicouleur, personnalisable en formes, qualité de vitrages, accessoires et décorations. Fabriquées dans nos usines françaises, ces portes-fenêtres bénéficient sous condition d'un délais de 14 jours maximum."
        },
        "urlKeyword": {
            "locale": "fr",
            "content": "porte-fenetre-excellence-pin-ou-chene-FPC713232"
        },
        "metaKeyword": {
            "locale": "fr",
            "content": "menuiseries,ouverture,bois"
        }
    },
    "partnumber": "FPC713232",
    "longDesc": {
        "locale": "fr",
        "content": "- Type de menuiserie : Porte-fenêtre sur mesure<BR/>- Matériau: Chêne<BR/>- Couleur: Finition claire ou foncé<BR/>- Type d'ouverture: Battante<BR/>- Type de vantaux : de 1 à 4, avec ou sans soubassement, à clé<BR/>- Type de pose : en applique, en rénovation, en tunnel ou en feuillure<BR/>- Epaisseur de l'ouvrant 56 mm aboutage intérieur et extérieur.<BR/>- Epaisseur du dormant 45mm aboutage intérieur et extérieur<BR/>- Double vitrage : 24 mm Énergie STAR® traité faible émissivité avec gaz argon et intercalaire<BR/>- Haute Isolation Thermique Uw 1,5,  Ug = 1.0<BR/>- Isolation Acoustique: AC1 (RA ; tr = 28 dB)<BR/>- Etanchéité: A*4 E*7B V*A3.<BR/>- Double joint d\u2019isolation thermique et acoustique<BR/>- Grille de ventilation : auto-réglable ou hydro-réglable, disponible en option<BR/><BR/><B>- Options disponibles en magasins sur la gamme Excellence sur mesure :<\/B><BR/>* Couleurs préférentielles : 2 finitions lasurées (à base d'eau sans solvant)<BR/>* Autres couleurs : 156 au choix, disponibles en mono et bicoloration<BR/>* Vitrages : Double vitrage isolation acoustique, contrôle solaire, SGG bioclean®, sécurité des biens et des personnes<BR/>* Ouverture oscillo-battante<BR/>* Petits bois intégrés, collés ou en cadre amovible, crémones décoratives<BR/>* Volet roulant : intégré à la fenêtre et coffre demi-linteau (pour le neuf) ou Rénopro (pour la rénovation)<BR/>* Formes spéciales : cintrées, trapèze, triangulaire et ?il-de-b?uf<BR/><BR/><B>- Délai Express Garanti :<\/B><BR/>* Votre fenêtre sur mesure disponible en express dans votre magasin partout en France en 14 jours maximum,consultez nos conseillers-experts en magasins"
    },
    "imageThumbnail": {
        "locale": "fr",
        "content": "/thumbnail/206/643/201206643.jpg"
    }
}}