{"product": {
    "categoriesParentList": {"categoryParent": {"categoryIdentifier": "portes-battantes_CCN0169"}},
    "action": "add",
    "itemList": {"item": [
        {
            "seoItem": {"urlKeyword": {
                "locale": "fr",
                "content": "bloc-porte-hetre-atria-vitre-3-carreaux-huisserie-72-h-204-xl-73-gauche-2547001"
            }},
            "sku": 2547001
        },
        {
            "seoItem": {"urlKeyword": {
                "locale": "fr",
                "content": "bloc-porte-hetre-atria-vitre-3-carreaux-huisserie-72-h-204-xl-73-droit-2547002"
            }},
            "sku": 2547002
        },
        {
            "seoItem": {"urlKeyword": {
                "locale": "fr",
                "content": "bloc-porte-hetre-atria-vitre-3-carreaux-huisserie-72-h-204-xl-83-gauche-2547011"
            }},
            "sku": 2547011
        },
        {
            "seoItem": {"urlKeyword": {
                "locale": "fr",
                "content": "bloc-porte-hetre-atria-vitre-3-carreaux-huisserie-72-h-204-xl-83-droit-2547012"
            }},
            "sku": 2547012
        },
        {
            "seoItem": {"urlKeyword": {
                "locale": "fr",
                "content": "bloc-porte-hetre-atria-vitre-3-carreaux-huisserie-72-h-204-xl-93-gauche-2547021"
            }},
            "sku": 2547021
        },
        {
            "seoItem": {"urlKeyword": {
                "locale": "fr",
                "content": "bloc-porte-hetre-atria-vitre-3-carreaux-huisserie-72-h-204-xl-93-droit-2547022"
            }},
            "sku": 2547022
        },
        {
            "seoItem": {"urlKeyword": {
                "locale": "fr",
                "content": "bloc-porte-hetre-atria-vitre-3-carreaux-huisserie-90-h-204-xl-73-gauche-2547031"
            }},
            "sku": 2547031
        },
        {
            "seoItem": {"urlKeyword": {
                "locale": "fr",
                "content": "bloc-porte-hetre-atria-vitre-3-carreaux-huisserie-90-h-204-xl-73-droit-2547032"
            }},
            "sku": 2547032
        },
        {
            "seoItem": {"urlKeyword": {
                "locale": "fr",
                "content": "bloc-porte-hetre-atria-vitre-3-carreaux-huisserie-90-h-204-xl-83-gauche-2547041"
            }},
            "sku": 2547041
        },
        {
            "seoItem": {"urlKeyword": {
                "locale": "fr",
                "content": "bloc-porte-hetre-atria-vitre-3-carreaux-huisserie-90-h-204-xl-83-droit-2547042"
            }},
            "sku": 2547042
        },
        {
            "seoItem": {"urlKeyword": {
                "locale": "fr",
                "content": "bloc-porte-hetre-atria-vitre-3-carreaux-huisserie-90-h-204-xl-93-gauche-2547051"
            }},
            "sku": 2547051
        }
    ]},
    "type": "STANDARD",
    "seo": {
        "imageAltText": {
            "locale": "fr",
            "content": "Bloc-porte Atria vitré - Portes"
        },
        "pageTitle": {
            "locale": "fr",
            "content": "Bloc-porte Atria vitré - Portes"
        },
        "metaDesc": {
            "locale": "fr",
            "content": "Un bloc-porte moderne avec de beaux niveaux de finition en hêtre à vernir et serrure à clé. Fabriqué dans nos usines françaises. Il existe en modèle 3 panneaux pleins."
        },
        "urlKeyword": {
            "locale": "fr",
            "content": "bloc-porte-atria-vitre-FPC1581925"
        }
    },
    "partnumber": "FPC1581925"
}}