{"product": {
    "categoriesParentList": {"categoryParent": {"categoryIdentifier": "accessoires-credences-CCN688487"}},
    "action": "add",
    "itemList": {"item": {
        "seoItem": {"urlKeyword": {
            "locale": "fr",
            "content": "ensemble-4-crochets-inox-pour-credence-design-3013860"
        }},
        "sku": 3013860
    }},
    "type": "STANDARD",
    "seo": {
        "imageAltText": {
            "locale": "fr",
            "content": "Sachet de 4 crochets pour barre de crédence Design - Cuisine"
        },
        "pageTitle": {
            "locale": "fr",
            "content": "Sachet de 4 crochets pour barre de crédence Design - Cuisine"
        },
        "metaDesc": {
            "locale": "fr",
            "content": "Suspendez accessoires, ustensiles, maniques et gagnez de la place grâce à ces 4 crochets pour barre de crédence design."
        },
        "urlKeyword": {
            "locale": "fr",
            "content": "sachet-de-4-crochets-FPC3013860"
        }
    },
    "partnumber": "FPC3013860"
}}