{"product": {
    "categoriesParentList": {"categoryParent": {"categoryIdentifier": "accessoires-salle-bains_CCN0027"}},
    "action": "add",
    "itemList": {"item": {
        "seoItem": {"urlKeyword": {
            "locale": "fr",
            "content": "porte-serviette-glamour-chrome-mobile-1126529"
        }},
        "sku": 1126529
    }},
    "type": "STANDARD",
    "seo": {
        "imageAltText": {
            "locale": "fr",
            "content": "Accessoires de salle de bains GLAMOUR - Porte-serviettes mobile - Salle de bains"
        },
        "pageTitle": {
            "locale": "fr",
            "content": "Accessoires de salle de bains GLAMOUR - Porte-serviettes mobile - Salle de bains"
        },
        "urlKeyword": {
            "locale": "fr",
            "content": "accessoires-de-salle-de-bains-glamour---porte-serviettes-mobile-FPC384267"
        }
    },
    "partnumber": "FPC384267"
}}