{"product": {
    "categoriesParentList": {"categoryParent": {"categoryIdentifier": "spots-CCN504783"}},
    "action": "add",
    "itemList": {"item": {
        "seoItem": {"urlKeyword": {
            "locale": "fr",
            "content": "spot-bijou-classe-2-ip44-1230436"
        }},
        "sku": 1230436
    }},
    "type": "STANDARD",
    "seo": {
        "imageAltText": {
            "locale": "fr",
            "content": "Spot pour miroir de salle de bains BIJOU - Salle de bains"
        },
        "pageTitle": {
            "locale": "fr",
            "content": "Spot pour miroir de salle de bains BIJOU - Salle de bains"
        },
        "metaDesc": {
            "locale": "fr",
            "content": "Apportez une touche chic à votre salle de bains avec cet éclairage par spot halogène en verre dépoli sur tige métal chromé, qui se fixe sur miroir ou armoire de toilette, vendus sur ce site."
        },
        "urlKeyword": {
            "locale": "fr",
            "content": "spot-pour-miroir-de-salle-de-bains-bijou-FPC1230436"
        }
    },
    "partnumber": "FPC1230436"
}}