{"product": {
    "categoriesParentList": {"categoryParent": {"categoryIdentifier": "ensembles-balneo_CCN0121"}},
    "action": "add",
    "itemList": {"item": {
        "seoItem": {"urlKeyword": {
            "locale": "fr",
            "content": "baignoire-balneo-lagune-diamant-2016-acryl-blanc-l-170-x-l-75-1242414"
        }},
        "sku": 1242414
    }},
    "type": "STANDARD",
    "seo": {
        "imageAltText": {
            "locale": "fr",
            "content": "Baignoire balnéo droite modèle LAGUNE système Diamant - Salle de bains"
        },
        "pageTitle": {
            "locale": "fr",
            "content": "Baignoire balnéo droite modèle LAGUNE système Diamant - Salle de bains"
        },
        "urlKeyword": {
            "locale": "fr",
            "content": "baignoire-balneo-droite-lagune-modele-diamant-FPC401910"
        },
        "metaKeyword": {
            "locale": "fr",
            "content": "bain,balneo"
        }
    },
    "partnumber": "FPC401910"
}}