{"product": {
    "categoriesParentList": {"categoryParent": {"categoryIdentifier": "modele-origine-CCN876878"}},
    "action": "add",
    "itemList": {"item": [
        {
            "seoItem": {"urlKeyword": {
                "locale": "fr",
                "content": "1-2-colonne-1-porte-niche-four-origine-creme-h-140-x-l-60-x-p-63-5105160"
            }},
            "sku": 5105160
        },
        {
            "seoItem": {"urlKeyword": {
                "locale": "fr",
                "content": "1-2-colonne-1-porte-niche-four-origine-creme-h-140-x-l-60-x-p-63-5105163"
            }},
            "sku": 5105163
        },
        {
            "seoItem": {"urlKeyword": {
                "locale": "fr",
                "content": "1-2-colonne-1-porte-niche-four-origine-gris-anthracite-h-140-x-l-60-x-p-63-5109160"
            }},
            "sku": 5109160
        },
        {
            "seoItem": {"urlKeyword": {
                "locale": "fr",
                "content": "1-2-colonne-1-porte-niche-four-origine-gris-anthracite-h-140-x-l-60-x-p-63-5109163"
            }},
            "sku": 5109163
        },
        {
            "seoItem": {"urlKeyword": {
                "locale": "fr",
                "content": "1-2-colonne-1-porte-niche-four-origine-bouleau-h-140-x-l-60-x-p-63-5143580"
            }},
            "sku": 5143580
        },
        {
            "seoItem": {"urlKeyword": {
                "locale": "fr",
                "content": "1-2-colonne-1-porte-niche-four-origine-bouleau-h-140-x-l-60-x-p-63-5143583"
            }},
            "sku": 5143583
        }
    ]},
    "type": "STANDARD",
    "seo": {
        "imageAltText": {
            "locale": "fr",
            "content": "Demi-colonne de cuisine pour four avec 2 tablettes ORIGINE - Cuisine"
        },
        "pageTitle": {
            "locale": "fr",
            "content": "Demi-colonne de cuisine pour four avec 2 tablettes ORIGINE - Cuisine"
        },
        "metaDesc": {
            "locale": "fr",
            "content": "Compacte, cette demi-colonne ORIGINE réalisée en panneau haute densité mélaminé avec chants antichoc permet d'intégrer un four en hauteur et de ranger plaques, grilles et moules."
        },
        "urlKeyword": {
            "locale": "fr",
            "content": "demi-colonne-de-cuisine-pour-four-avec-2-tablettes-origine-FPC5143580"
        }
    },
    "partnumber": "FPC5143580"
}}