{"product": {
    "categoriesParentList": {"categoryParent": [
        {"categoryIdentifier": "electriques-CCN688916"},
        {"categoryIdentifier": "electriques-CCN688919"}
    ]},
    "action": "add",
    "itemList": {"item": [
        {
            "seoItem": {"urlKeyword": {
                "locale": "fr",
                "content": "seche-serviettes-electrique-soufflant-madras-500-1000w-blanc-h-109-4x-l-50-1242345"
            }},
            "sku": 1242345
        },
        {
            "seoItem": {"urlKeyword": {
                "locale": "fr",
                "content": "seche-serviettes-electrique-soufflant-madras750-1000w-blanc-h-151-7-x-l-50-1242346"
            }},
            "sku": 1242346
        },
        {
            "seoItem": {"urlKeyword": {
                "locale": "fr",
                "content": "seche-serviettes-electrique-soufflant-madras-500-1000w-black-flash-h-109-4xl-50-1244586"
            }},
            "sku": 1244586
        },
        {
            "seoItem": {"urlKeyword": {
                "locale": "fr",
                "content": "seche-serviettes-electrique-soufflant-madras-750-1000w-black-flash-h-151-7xl-50-1244587"
            }},
            "sku": 1244587
        },
        {
            "seoItem": {"urlKeyword": {
                "locale": "fr",
                "content": "seche-serviettes-electrique-souffl-madras-500-1000w-grey-aluminium-h109-4xl50-1244588"
            }},
            "sku": 1244588
        },
        {
            "seoItem": {"urlKeyword": {
                "locale": "fr",
                "content": "seche-serviettes-electrique-souffl-madras-750-1000w-grey-aluminium-h151-7xl50-1244589"
            }},
            "sku": 1244589
        },
        {
            "seoItem": {"urlKeyword": {
                "locale": "fr",
                "content": "seche-serviettes-electrique-soufflant-madras-500w-1000w-dark-brown-h-109-4xl-50-1244591"
            }},
            "sku": 1244591
        },
        {
            "seoItem": {"urlKeyword": {
                "locale": "fr",
                "content": "seche-serviettes-electrique-soufflant-madras-750w-1000w-dark-brown-h-151-7xl-50-1244592"
            }},
            "sku": 1244592
        }
    ]},
    "type": "STANDARD",
    "seo": {
        "imageAltText": {
            "locale": "fr",
            "content": "Sèche-serviettes MADRAS électrique soufflant - Salle de bains"
        },
        "pageTitle": {
            "locale": "fr",
            "content": "Sèche-serviettes MADRAS électrique soufflant - Salle de bains"
        },
        "metaDesc": {
            "locale": "fr",
            "content": "Un radiateur sèche-serviettes électrique Acova, extra-plat pour s'adapter à toutes les tailles de salle de bains. Avec fonction soufflante tout confort et commande infrarouge, il est disponible en 2 puissances."
        },
        "urlKeyword": {
            "locale": "fr",
            "content": "seche-serviette-madras--soufflant-FPC429300"
        }
    },
    "partnumber": "FPC429300"
}}