{"product": {
    "categoriesParentList": {"categoryParent": {"categoryIdentifier": "vidages_CCN0094"}},
    "action": "add",
    "itemList": {"item": {
        "seoItem": {"urlKeyword": {
            "locale": "fr",
            "content": "vidage-evier-2-bacs-universel-a-cable-diametre-90-1242239"
        }},
        "sku": 1242239
    }},
    "type": "STANDARD",
    "seo": {
        "imageAltText": {
            "locale": "fr",
            "content": "Vidage universel automatique gain de place pour évier 1,5 ou 2 bacs - Cuisine"
        },
        "pageTitle": {
            "locale": "fr",
            "content": "Vidage universel automatique gain de place pour évier 1,5 ou 2 bacs - Cuisine"
        },
        "urlKeyword": {
            "locale": "fr",
            "content": "vidage-universel-automatique-2-bacs-FPC426910"
        }
    },
    "partnumber": "FPC426910"
}}